{
    "twitterId": "@aomichi_akato",
    "channelDescription": "だおらーっす！\nバーチャル学徒Youtuberの青道アカトだ！\n夢を持つみんなを楽しい動画で応援するぞ！\nいろいろ未熟だけど頑張り続けていくんでよろしくどすこいベイベー！！\n\n【Twitter】\nhttps://twitter.com/aomichi_akato\n\n【質問箱】\nhttps://peing.net/ja/aomichi_akato",
    "views": "109435",
    "heatmap": [
        {
            "videoId": "Jqj6Z3YHWiY",
            "title": "【ぷよぷよ～ん】みんながテトリスやってる中『ぷよぷよ』やる！！【実況】 どすこいLIVE!!#55",
            "publishedAt": "2019-03-01",
            "viewCount": "423"
        },
        {
            "videoId": "D-iGJObUaXQ",
            "title": "【第4部】アカト24h【青道アカト1周年記念】",
            "publishedAt": "2019-02-24",
            "viewCount": "2060"
        },
        {
            "videoId": "zxuJrLRY2Jo",
            "title": "【第3部-3】アカト24h【青道アカト1周年記念】",
            "publishedAt": "2019-02-24",
            "viewCount": "923"
        },
        {
            "videoId": "N9kD0O6AU8Q",
            "title": "【第3部-2】アカト24h【青道アカト1周年記念】",
            "publishedAt": "2019-02-23",
            "viewCount": "761"
        },
        {
            "videoId": "fea8sWP1n54",
            "title": "【第3部-1】アカト24h【青道アカト1周年記念】",
            "publishedAt": "2019-02-23",
            "viewCount": "336"
        },
        {
            "videoId": "5ouQSpaKakY",
            "title": "【第2部】アカト24h【青道アカト1周年記念】",
            "publishedAt": "2019-02-23",
            "viewCount": "1431"
        },
        {
            "videoId": "6TwQztXhh8s",
            "title": "【第1部-2】アカト24h【青道アカト1周年記念】",
            "publishedAt": "2019-02-23",
            "viewCount": "1343"
        },
        {
            "videoId": "bW3HO5HSVmk",
            "title": "【第1部-1】アカト24h【青道アカト1周年記念】",
            "publishedAt": "2019-02-23",
            "viewCount": "2083"
        },
        {
            "videoId": "eW7tPza5Ros",
            "title": "【ドミニオン】今期流行らせたいカードゲームで陰謀に打ち勝つ！！【拡張：陰謀】どすこいLIVE!!#54",
            "publishedAt": "2019-02-12",
            "viewCount": "470"
        },
        {
            "videoId": "iErGly4jbok",
            "title": "【ハイテンション不可避！！】スマブラ買えてないと思ったらスマブラ持ってた件【ダイジェスト版】",
            "publishedAt": "2019-02-05",
            "viewCount": "660"
        },
        {
            "videoId": "txceUZUNDT8",
            "title": "【ドミニオン】皆がシャドバやってる中、伝説のカードゲームやる【説明】どすこいLIVE!!#52",
            "publishedAt": "2019-01-29",
            "viewCount": "603"
        },
        {
            "videoId": "GMShNc0AKAw",
            "title": "「元気がうるさいお喋りノンストップポケモンLet&#39;s Go!ピカチュウ実況part2」どすこいLIVE!!#51",
            "publishedAt": "2019-01-28",
            "viewCount": "363"
        },
        {
            "videoId": "XY2QHJVAiE0",
            "title": "後編「元気がうるさいお喋りノンストップポケモンLet&#39;s Go!ピカチュウ実況part1」どすこいLIVE!!#50",
            "publishedAt": "2019-01-24",
            "viewCount": "217"
        },
        {
            "videoId": "T2QDT69DpV0",
            "title": "前編「元気がうるさいお喋りノンストップポケモンLet&#39;s Go!ピカチュウ実況part1」どすこいLIVE!!#50",
            "publishedAt": "2019-01-24",
            "viewCount": "473"
        },
        {
            "videoId": "xdpUGMDG51A",
            "title": "「ひまっしゃい！二次会inあおあか学園放送！！」",
            "publishedAt": "2019-01-16",
            "viewCount": "938"
        },
        {
            "videoId": "0FfbVriB5x0",
            "title": "「【NOISY KNIGHT】カリスマガクトVTuber・SOUOND【ホストクラブ】」どすこいLIVE!!#49",
            "publishedAt": "2019-01-15",
            "viewCount": "737"
        },
        {
            "videoId": "5T7MVLKJRfc",
            "title": "「初SWITCHテスト配信！！元気がうるさいお喋りノンストップスマブラSP実況」どすこいLIVE!!#48",
            "publishedAt": "2019-01-13",
            "viewCount": "731"
        },
        {
            "videoId": "9q8UZGKnI3Q",
            "title": "「新年騒々お喋りノンストップ雑談2019初配信」どすこいLIVE!!#47",
            "publishedAt": "2019-01-08",
            "viewCount": "641"
        },
        {
            "videoId": "ai5F7WMIRcQ",
            "title": "「アカトの騒音クリスマス～鼓膜破壊すごろくもあるよ～」どすこいLIVE!!#46",
            "publishedAt": "2018-12-26",
            "viewCount": "644"
        },
        {
            "videoId": "zqkGozM00P8",
            "title": "「青道おにいさんのゲリラおうたの時間」どすこいLIVE!!#45.5",
            "publishedAt": "2018-12-20",
            "viewCount": "600"
        },
        {
            "videoId": "By7H2AHePbI",
            "title": "「元気がうるさいお喋りノンストップ超魔界村実況ファイナル～M-1決勝～」どすこいLIVE!!#45",
            "publishedAt": "2018-12-13",
            "viewCount": "702"
        },
        {
            "videoId": "KTz2wiSyqwo",
            "title": "「スマブラ買えてないと思ったらスマブラ持ってた件」どすこいLIVE!!#44",
            "publishedAt": "2018-12-08",
            "viewCount": "1135"
        },
        {
            "videoId": "8BZSwt1aD4w",
            "title": "「VTuberドラフト会議(ソロ)～お試し解説～」どすこいLIVE!!#43",
            "publishedAt": "2018-12-03",
            "viewCount": "874"
        },
        {
            "videoId": "sb_1BPb0myo",
            "title": "「元気がうるさいお喋りノンストップ雑談～FANBOXボイス案とか自分の声を探る～」どすこいLIVE!!#42",
            "publishedAt": "2018-11-23",
            "viewCount": "658"
        },
        {
            "videoId": "4akPy6rbzFo",
            "title": "【あおあか学園放送】「元気がうるさいお喋りノンストップ超魔界村実況」どすこいLIVE!!#41",
            "publishedAt": "2018-11-15",
            "viewCount": "659"
        },
        {
            "videoId": "sRv6VlwKK1A",
            "title": "【あおあか学園放送】「元気がうるさいお喋りノンストップファイナルファイト実況リベンジ」どすこいLIVE!!#40",
            "publishedAt": "2018-11-07",
            "viewCount": "553"
        },
        {
            "videoId": "plW52P-qSSU",
            "title": "【あおあか学園放送】「元気がうるさいお喋りノンストップマイクラ実況！！#3」どすこいLIVE!!#39後編",
            "publishedAt": "2018-11-05",
            "viewCount": "508"
        },
        {
            "videoId": "bbBLAXj9fB8",
            "title": "【あおあか学園放送】「元気がうるさいお喋りノンストップマイクラ実況！！#3」どすこいLIVE!!#39前編",
            "publishedAt": "2018-11-05",
            "viewCount": "259"
        },
        {
            "videoId": "DvCDb14VNGc",
            "title": "【あおあか学園放送】「元気がうるさいお喋りノンストップファイナルファイト実況」どすこいLIVE!!#38",
            "publishedAt": "2018-10-25",
            "viewCount": "676"
        },
        {
            "videoId": "APIhettgBQA",
            "title": "【あおあか学園放送】「元気がうるさいお喋りノンストップゲリラじお～マシュマロばりむしゃァ～」どすこいLIVE!!#37",
            "publishedAt": "2018-10-19",
            "viewCount": "554"
        },
        {
            "videoId": "ICvdI-4kz8c",
            "title": "【あおあか学園放送】「青道アカト 怒リィ新校～Angry curry new school～」どすこいLIVE!!#36",
            "publishedAt": "2018-10-13",
            "viewCount": "1302"
        },
        {
            "videoId": "sZUF47WGEx4",
            "title": "【あおあか学園放送】「元気がうるさいお喋りノンストップゲリラじお～ぽんぽこ24リターンズお疲れさ卍トーク～」どすこいLIVE!!#35",
            "publishedAt": "2018-10-08",
            "viewCount": "1685"
        },
        {
            "videoId": "GsBzHOZn9xM",
            "title": "【あおあか学園放送】「元気がうるさいお喋りノンストップゲリラじお」どすこいLIVE!!#34",
            "publishedAt": "2018-10-04",
            "viewCount": "657"
        },
        {
            "videoId": "jV16ZUrz9KQ",
            "title": "【男子高校生3人組VTuber】帰ってきた！！バーチャルDK3!!!【コラボ雑談】",
            "publishedAt": "2018-09-30",
            "viewCount": "645"
        },
        {
            "videoId": "VH_Q3bp-nrQ",
            "title": "【あおあか学園放送】「元気がうるさいお喋りノンストップマイクラ実況！！#2」どすこいLIVE!!#33",
            "publishedAt": "2018-09-27",
            "viewCount": "670"
        },
        {
            "videoId": "RhMj72FX5l8",
            "title": "【あおあか学園放送】「青道文庫～読書の秋スペシャル～」どすこいLIVE!!#32",
            "publishedAt": "2018-09-20",
            "viewCount": "989"
        },
        {
            "videoId": "VCPtRywPG6w",
            "title": "【あおあか学園放送】「マイクラ初体験赤青マン！！！！！」どすこいLIVE!!#31",
            "publishedAt": "2018-09-19",
            "viewCount": "564"
        },
        {
            "videoId": "hwvaWyFYdd0",
            "title": "【あおあか学園放送】「マイクラ配信が満足に出来ないノンストップ雑談配信(放送事故)」どすこいLIVE!!#30.5",
            "publishedAt": "2018-09-18",
            "viewCount": "700"
        },
        {
            "videoId": "asyqqpYl99s",
            "title": "【あおあか学園放送】「VTuberパーティで旅するドラゴンクエスト3実況part2」どすこいLIVE!!#30",
            "publishedAt": "2018-09-10",
            "viewCount": "949"
        }
    ]
}