{
    "twitterId": "@hosakimenmavt",
    "channelDescription": "新人Vtuberの保崎メンマ（ほさきめんま）です(๑•⌄•๑)！よろしくね🍥\n好きなものは音楽とラーメンと・・・あとはね、えっと、なんだったっけ…⁇\nチャンネル登録してくれたらすごく嬉しい🍜٩(๑•π•๑)ｵｶﾜﾘ‼\n助けてくれた魔法使いさん✨→@blaulac",
    "views": "18773",
    "heatmap": [
        {
            "videoId": "7hfeVgM8kzk",
            "title": "だい１わ　「はじめまして、保崎メンマです！」",
            "publishedAt": "2019-02-17",
            "viewCount": "2985"
        },
        {
            "videoId": "BYtlzGoKz9U",
            "title": "ロキ/保崎メンマ【歌ってみた】",
            "publishedAt": "2019-02-16",
            "viewCount": "7932"
        },
        {
            "videoId": "YztSL9di6Ko",
            "title": "【歌ってみた🎄】 ウェルカム・トゥ・クリスマス - 保崎メンマ【ディズニー】",
            "publishedAt": "2018-12-25",
            "viewCount": "3002"
        },
        {
            "videoId": "XnKMRQq182U",
            "title": "Menma is revive.",
            "publishedAt": "2018-11-18",
            "viewCount": "4789"
        }
    ]
}