{
    "twitterId": "@Pati_kasikoman9",
    "channelDescription": "●「Patiパチ」という名前でゲーム実況をしてます。\n\n●Twitter→https://twitter.com/Pati_kasikoman9\n\n●スポンサーになる→https://gaming.youtube.com/channel/UC...\n※約400円のスポンサーになるとオリジナル絵文字が名前の隣に表示されたりコメントで使うことができます！くわしくは→\n\n●お誘いやお仕事等はメールまたはTwitterのダイレクトメッセージよりお願いします。\n\n-楽曲提供-\n▶DOVASYNDROME/ https://dova-s.jp/\n▶NCS/ https://youtu.be/NDhxjHP77sU\n▶MrSuicideSheep / https://www.youtube.com/user/MrSuicideSheep \n▶Wingless Serap/ https://wingless-seraph.net\n▶H/MIX GALLERY/ http://www.hmix.net/music_gallery\n▶その他沢山",
    "views": "1338109",
    "heatmap": [
        {
            "videoId": "MK19Qeobmqs",
            "title": "最近、人轢きぎみ。　-PUBG MONTAGE-",
            "publishedAt": "2019-02-09",
            "viewCount": "249"
        },
        {
            "videoId": "YMjFLV7qpcI",
            "title": "謝罪",
            "publishedAt": "2019-01-19",
            "viewCount": "608"
        },
        {
            "videoId": "jgC01szaGsg",
            "title": "嚙み合わない2人のダンジョン攻略　- やすぱちのチョコクエ #1 -",
            "publishedAt": "2019-01-01",
            "viewCount": "879"
        },
        {
            "videoId": "HAxCPOxrNbs",
            "title": "クリスマスにやることと言えば...？",
            "publishedAt": "2018-12-25",
            "viewCount": "241"
        },
        {
            "videoId": "J-XNZ3EI-Ek",
            "title": "【大問題】戦闘シーンが全くない問題のPUBG実況",
            "publishedAt": "2018-12-23",
            "viewCount": "200"
        },
        {
            "videoId": "l2JDHTG1OD0",
            "title": "初心者向け最強ファイター『ロイ』解説！！【コンボ/立ち回り】",
            "publishedAt": "2018-12-19",
            "viewCount": "2243"
        },
        {
            "videoId": "NeY5Fe17zxs",
            "title": "【スマブラSP】最強のワザが決定した件について",
            "publishedAt": "2018-12-12",
            "viewCount": "137"
        },
        {
            "videoId": "2bkbUrroaEQ",
            "title": "【スマブラSP】VIPマッチでイカちゃん最強めざす！！！",
            "publishedAt": "2018-12-09",
            "viewCount": "189"
        },
        {
            "videoId": "0eyrdOwL4vg",
            "title": "【スマブラSP】インクリングのボムが最強すぎる動画【必見】",
            "publishedAt": "2018-12-08",
            "viewCount": "846"
        },
        {
            "videoId": "RYkd8TEvbmI",
            "title": "バギーと風船で最高得点目指してみた  -Fortnite-",
            "publishedAt": "2018-12-03",
            "viewCount": "235"
        },
        {
            "videoId": "CfoJZhf957A",
            "title": "【狂気】おじいさんが好きなゲイと行くDBD",
            "publishedAt": "2018-11-11",
            "viewCount": "276"
        },
        {
            "videoId": "rCbax0VEgQ4",
            "title": "殺意のコンボ！グリンと勝負！！ -スマブラ実況-",
            "publishedAt": "2018-11-10",
            "viewCount": "200"
        },
        {
            "videoId": "0ccqGcqhDPk",
            "title": "【マリオメーカー】静凛の鬼畜ステージに挑戦してみた！！",
            "publishedAt": "2018-10-25",
            "viewCount": "686"
        },
        {
            "videoId": "w9WtqUAx050",
            "title": "ビルから落ちるミライアカリを助けろ！！　-GMOD-",
            "publishedAt": "2018-10-20",
            "viewCount": "536"
        },
        {
            "videoId": "hlYj-KOg5pE",
            "title": "3年間放置したチャージャーは克服できるのか！？ -スプラトゥーン2-",
            "publishedAt": "2018-10-10",
            "viewCount": "234"
        },
        {
            "videoId": "-_LrnJMGzcU",
            "title": "【Fortnite】シーズン5の思い出【シーン集】",
            "publishedAt": "2018-09-29",
            "viewCount": "724"
        },
        {
            "videoId": "dpfovRNYtIQ",
            "title": "【スキンチート】チートスキンを使ってみた【フォートナイト】【ハック】",
            "publishedAt": "2018-09-27",
            "viewCount": "12040"
        },
        {
            "videoId": "YU9sABJMpag",
            "title": "ファールボールに全速力で追いかけるチーム",
            "publishedAt": "2018-09-25",
            "viewCount": "170"
        },
        {
            "videoId": "xOgnJ-aqKcQ",
            "title": "スマブラSP新キャラ「しずえ」使ってみた！！！！！【スマブラ / ハック】",
            "publishedAt": "2018-09-19",
            "viewCount": "5820"
        },
        {
            "videoId": "_H4nG6GJKa4",
            "title": "スマブラSPの新キャラ「クロム」使ってみた！！！【スマブラ/ハック】",
            "publishedAt": "2018-09-17",
            "viewCount": "2760"
        },
        {
            "videoId": "xrbnl1gX6Og",
            "title": "過去最高ブキ！スプラシューターベッチューがヤバすぎる！！　-スプラトゥーン2-",
            "publishedAt": "2018-09-15",
            "viewCount": "287"
        },
        {
            "videoId": "G5hAIdnJECY",
            "title": "スマブラSPの新キャラ「キングクルール」使ってみた！！！【スマブラ/ハック】",
            "publishedAt": "2018-09-14",
            "viewCount": "2337"
        },
        {
            "videoId": "gLt6PVnX4xI",
            "title": "【発狂】マイクラで出来るスプラトゥーン！！！【実況】",
            "publishedAt": "2018-09-09",
            "viewCount": "206"
        },
        {
            "videoId": "bwuL5z_NLzk",
            "title": "金アサルトが最強！瞬殺ブキで❔❔Killビクロ！  -フォートナイト スイッチ版-",
            "publishedAt": "2018-09-06",
            "viewCount": "264"
        }
    ]
}