{
    "twitterId": "@A_BOX_LAND",
    "channelDescription": "フハハハ！　ヴァーチャルYoutuberを始めたぞ！　これでゆくゆくは世界征服を目指すのだぁ！\n\ntwitter　https://twitter.com/A_BOX_LAND",
    "views": "1981494",
    "heatmap": [
        {
            "videoId": "1cthn9Q7P0g",
            "title": "M☆T☆G　踊るプレミ大走査線",
            "publishedAt": "2019-03-02",
            "viewCount": "2241"
        },
        {
            "videoId": "L3K_SnDf3Fo",
            "title": "「Virtual Collection Stage1」YouTube配信視点",
            "publishedAt": "2019-03-02",
            "viewCount": "4729"
        },
        {
            "videoId": "ESnZqKfMmrU",
            "title": "天空に巨大建造物",
            "publishedAt": "2019-02-24",
            "viewCount": "4921"
        },
        {
            "videoId": "HyJkCSbPkwA",
            "title": "ダブルクロスの余韻に浸りながらapexやっても良いのですか！？with叶",
            "publishedAt": "2019-02-17",
            "viewCount": "3535"
        },
        {
            "videoId": "nNZsUdp45QE",
            "title": "Daemon X Machinaの体験版をプレイした大魔王、その理由に涙が止まらない。",
            "publishedAt": "2019-02-14",
            "viewCount": "3764"
        },
        {
            "videoId": "9B-fvRHPIH0",
            "title": "大魔王とヒーローとゲーマーのそれいけApex",
            "publishedAt": "2019-02-10",
            "viewCount": "15124"
        },
        {
            "videoId": "F_rR7SQ42Fs",
            "title": "ゆるくら会 #8 大魔王襲来",
            "publishedAt": "2019-02-08",
            "viewCount": "3647"
        },
        {
            "videoId": "SQs-HkPoU5o",
            "title": "ゆるくら会 #8 大魔王襲来",
            "publishedAt": "2019-02-08",
            "viewCount": "1220"
        },
        {
            "videoId": "zL2ESlRGd9k",
            "title": "コレの新衣装を考えてみる",
            "publishedAt": "2019-02-06",
            "viewCount": "4034"
        },
        {
            "videoId": "MC01YhpvAhU",
            "title": "囚人組黒い砂漠レベリング【あっくん大魔王視点】",
            "publishedAt": "2019-02-03",
            "viewCount": "4854"
        },
        {
            "videoId": "10ouPs5J8p4",
            "title": "異性のメールに♡があるだけで勘ぐってしまう大魔王のぎゃる☆がん",
            "publishedAt": "2019-02-02",
            "viewCount": "7342"
        },
        {
            "videoId": "05ZBOnsPDbQ",
            "title": "【あっくん大魔王視点】PUBGだぜ",
            "publishedAt": "2019-02-01",
            "viewCount": "2201"
        },
        {
            "videoId": "ph_Skf14GFE",
            "title": "【あっくん大魔王】頭脳縛りシャドウバース",
            "publishedAt": "2019-01-30",
            "viewCount": "3303"
        },
        {
            "videoId": "VzTMOgiAYoE",
            "title": "あっくん大魔王の公開収録その1",
            "publishedAt": "2019-01-30",
            "viewCount": "3820"
        },
        {
            "videoId": "9oPxbhm1V5I",
            "title": "「Dragon Marked For Death」をVTuber四人でマルチプレイ",
            "publishedAt": "2019-01-27",
            "viewCount": "6580"
        },
        {
            "videoId": "48Xvyn-Q9SI",
            "title": "ゲーマーの心躍る横スクロールアクションRPG「Dragon Marked For Death」を先行プレイ",
            "publishedAt": "2019-01-27",
            "viewCount": "2813"
        },
        {
            "videoId": "NKsNsgJYwJ8",
            "title": "【PUBG】楽しい楽しいPUBGの時間",
            "publishedAt": "2019-01-14",
            "viewCount": "4017"
        },
        {
            "videoId": "yqiyqHN7kWs",
            "title": "【PUBG】ソロドン食べたい【画質テスト】",
            "publishedAt": "2019-01-13",
            "viewCount": "1660"
        },
        {
            "videoId": "UW9f49RqyjE",
            "title": "【雑談】今宵は凄い日だったぞ",
            "publishedAt": "2019-01-09",
            "viewCount": "6573"
        },
        {
            "videoId": "H7IAVx1xr3g",
            "title": "あっくん大魔王1周年",
            "publishedAt": "2019-01-07",
            "viewCount": "18188"
        },
        {
            "videoId": "-aZoNc48ZL0",
            "title": "天魔機忍ver.Gの1/6の夢旅人2002",
            "publishedAt": "2019-01-07",
            "viewCount": "37810"
        },
        {
            "videoId": "AT4yaV1R6no",
            "title": "あっくん大魔王のダラダラ新年雑談",
            "publishedAt": "2019-01-02",
            "viewCount": "5894"
        },
        {
            "videoId": "3MvGkyMRElw",
            "title": "【PUBG】新春ごちゃまぜPUBG【あっくん大魔王視点】",
            "publishedAt": "2019-01-01",
            "viewCount": "7341"
        },
        {
            "videoId": "KsclLapqnfs",
            "title": "スマブラ見たらスマブラを無性にやりたくなるのは深夜のラーメン理論",
            "publishedAt": "2018-12-15",
            "viewCount": "3273"
        },
        {
            "videoId": "yY1-MpRYHvk",
            "title": "アドベンチャーモードをクリアした大魔王のスマブラ",
            "publishedAt": "2018-12-08",
            "viewCount": "2371"
        },
        {
            "videoId": "2rvka-QWpfs",
            "title": "新作スマブラを30分前くらいから待機しながらなんかもううわぁ！",
            "publishedAt": "2018-12-06",
            "viewCount": "8295"
        },
        {
            "videoId": "gV51UgTKDwM",
            "title": "色々ありすぎたのでクールダウン雑談",
            "publishedAt": "2018-12-01",
            "viewCount": "3429"
        },
        {
            "videoId": "j5As-gZA1Qo",
            "title": "【#ピカV杯】あっくん大魔王第二回戦",
            "publishedAt": "2018-12-01",
            "viewCount": "1787"
        },
        {
            "videoId": "iKJxFT9Bt-Q",
            "title": "【#ピカV杯】あっくん大魔王第一回戦",
            "publishedAt": "2018-12-01",
            "viewCount": "3335"
        },
        {
            "videoId": "5_q-F4TtaoM",
            "title": "ポケモン大会が近くて興奮しまくり大魔王",
            "publishedAt": "2018-11-30",
            "viewCount": "1586"
        },
        {
            "videoId": "5jD987w-w6A",
            "title": "ポケモン大会が近くて興奮しまくり大魔王",
            "publishedAt": "2018-11-30",
            "viewCount": "1041"
        },
        {
            "videoId": "4IrI0tOBW-M",
            "title": "ポケモン大会に向けてのパーティを決めたのであった",
            "publishedAt": "2018-11-29",
            "viewCount": "7382"
        },
        {
            "videoId": "XdRj8Jjo_8E",
            "title": "【あっくん大魔王視点】VTuber囚人組、マスターに捧げるドン勝【PUBG】",
            "publishedAt": "2018-11-25",
            "viewCount": "4255"
        },
        {
            "videoId": "yJV5g0gLQDQ",
            "title": "マイクラ1チャンク建造",
            "publishedAt": "2018-11-24",
            "viewCount": "4389"
        },
        {
            "videoId": "OMjEr9_1Y8g",
            "title": "【#マイクラ絶望的サバイバル】　深夜のギブアップ宣伝",
            "publishedAt": "2018-11-23",
            "viewCount": "4054"
        },
        {
            "videoId": "GJIs8tRUWzs",
            "title": "【#マイクラ絶望的サバイバル】　一日目その3",
            "publishedAt": "2018-11-23",
            "viewCount": "4483"
        },
        {
            "videoId": "t6N19_zQd3A",
            "title": "【#マイクラ絶望的サバイバル】　一日目その3",
            "publishedAt": "2018-11-23",
            "viewCount": "2343"
        },
        {
            "videoId": "IHQglmh6GnE",
            "title": "【#マイクラ絶望的サバイバル】　一日目その2",
            "publishedAt": "2018-11-23",
            "viewCount": "5074"
        },
        {
            "videoId": "qlJ65GnejRg",
            "title": "【#マイクラ絶望的サバイバル】　一日目その2",
            "publishedAt": "2018-11-23",
            "viewCount": "10447"
        },
        {
            "videoId": "8i7oVLvcGx8",
            "title": "【雑談配信】有名タイトルを食わず嫌いすると損する説【あっくん大魔王】",
            "publishedAt": "2018-11-21",
            "viewCount": "4872"
        },
        {
            "videoId": "g3wU7cwdna8",
            "title": "大魔王の初めてのポケモンその3【ポケモンレッツゴーイーブイ】",
            "publishedAt": "2018-11-20",
            "viewCount": "7735"
        },
        {
            "videoId": "lpEw5xnGboM",
            "title": "大魔王の初めてのポケモンその2【ポケモンレッツゴーイーブイ】",
            "publishedAt": "2018-11-20",
            "viewCount": "6039"
        },
        {
            "videoId": "YI6P5YJVrv0",
            "title": "大魔王の初めてのポケモン【ポケモンレッツゴーイーブイ】",
            "publishedAt": "2018-11-19",
            "viewCount": "7817"
        },
        {
            "videoId": "7tkWMqW7CAA",
            "title": "【あっくん大魔王】三連休企画発表会",
            "publishedAt": "2018-11-18",
            "viewCount": "4097"
        },
        {
            "videoId": "uOchflMgQo8",
            "title": "吾輩の力を最大限に生かしてくれる杖ください【Vlend】",
            "publishedAt": "2018-11-11",
            "viewCount": "5677"
        },
        {
            "videoId": "ctonApu-gPE",
            "title": "渋谷大魔王withえいむ【あっくん大魔王視点】",
            "publishedAt": "2018-11-09",
            "viewCount": "3482"
        },
        {
            "videoId": "sW-fj1Imq6k",
            "title": "あっくん大魔王の部屋【雑談】",
            "publishedAt": "2018-11-08",
            "viewCount": "8402"
        },
        {
            "videoId": "jMQWXX0yrDw",
            "title": "【#Vtuber囚人組】囚人が八人、何も起きないはずが無く……【あっくん大魔王視点】",
            "publishedAt": "2018-11-08",
            "viewCount": "12044"
        },
        {
            "videoId": "iR-2Fiad6SM",
            "title": "【あっくん大魔王】心の均衡を保つために絶叫したらオギャってみる【Knock-Knock】",
            "publishedAt": "2018-10-31",
            "viewCount": "10334"
        },
        {
            "videoId": "R3UzqZjtxiw",
            "title": "【あっくん大魔王】ミサイル艦を建造するのだその２【FTD】",
            "publishedAt": "2018-10-26",
            "viewCount": "2741"
        },
        {
            "videoId": "BXikNr7ZD6g",
            "title": "【PUBG】VTuber最強決定戦！！【オッパゲ淫魔王】",
            "publishedAt": "2018-10-20",
            "viewCount": "13045"
        },
        {
            "videoId": "CAdQFm_2dCI",
            "title": "【PUBG】オッパゲ淫魔王で大会練習！",
            "publishedAt": "2018-10-18",
            "viewCount": "5504"
        },
        {
            "videoId": "m4b8AXGI1OM",
            "title": "【PUBG】オッパゲ淫魔王で",
            "publishedAt": "2018-10-18",
            "viewCount": "2879"
        },
        {
            "videoId": "rA6KQZVsy0I",
            "title": "【あっくん大魔王】ミサイル艦を建造するのだ【FTD】",
            "publishedAt": "2018-10-15",
            "viewCount": "3119"
        },
        {
            "videoId": "3f6fWmsJr50",
            "title": "【あっくん大魔王】声が枯れると色々大変だ【雑談】",
            "publishedAt": "2018-10-12",
            "viewCount": "4521"
        },
        {
            "videoId": "LDdz2TMF3Qs",
            "title": "【あっくん大魔王】新宿の服屋は異世界ダンジョンだった【雑談】",
            "publishedAt": "2018-09-28",
            "viewCount": "6963"
        },
        {
            "videoId": "uIq1IXc1lfU",
            "title": "あっくん大魔王の部屋【雑談】",
            "publishedAt": "2018-09-20",
            "viewCount": "7458"
        },
        {
            "videoId": "RJr_HtnKcXA",
            "title": "あっくん大魔王VS激辛MAXEND",
            "publishedAt": "2018-09-09",
            "viewCount": "25824"
        }
    ]
}