[
    {
        "channelId": "UC4YaOt1yT-ZeyB0OmxHgolA",
        "twitterId": "@aichan_nel"
    },
    {
        "channelId": "UCbFwe3COkDrbNsbMyGNCsDg",
        "twitterId": "@aichan_nel"
    },
    {
        "channelId": "UCQYADFw7xEJ9oZSM5ZbqyBw",
        "twitterId": "@_KaguyaLuna"
    },
    {
        "channelId": "UCMYtONm441rBogWK_xPH9HA",
        "twitterId": "@MiraiAkari_prj"
    },
    {
        "channelId": "UCLhUvJ_wO9hOvv_yYENu4fQ",
        "twitterId": "@SIROyoutuber"
    },
    {
        "channelId": "UCevD0wKzJFpfIkvHOiQsfLQ",
        "twitterId": "@Nekomiya_Hinata"
    },
    {
        "channelId": "UC2ZVDmnoZAOdLt7kI7Uaqog",
        "twitterId": "@Kaede_gamebu"
    },
    {
        "channelId": "UCFv2z4iM5vHrS8bZPq4fHQQ",
        "twitterId": "@HimeTanaka_HH"
    },
    {
        "channelId": "UCy5lOmEQoivK5XK7QCaRKug",
        "twitterId": "@APP_Yomemi"
    },
    {
        "channelId": "UCD-miitqNY3nyukJ4Fnf4_A",
        "twitterId": "@MitoTsukino"
    },
    {
        "channelId": "UCHTnX0CSX_KObo5I9WuZ64g",
        "twitterId": "@yuni_vsinger"
    },
    {
        "channelId": "UCt8tmsv8kL9Nc1sxvCo9j4Q",
        "twitterId": "@kemomimi_oukoku"
    },
    {
        "channelId": "UCCebk1_w5oiMUTRxdNJq0sA",
        "twitterId": "@kokoa_domyoji"
    },
    {
        "channelId": "UCp6993wxpyDPHUpavwDFqgg",
        "twitterId": "@tokino_sora"
    },
    {
        "channelId": "UC3Ruo_5doyu514PesWGvCAg",
        "twitterId": "@fuji_aoi_0618"
    },
    {
        "channelId": "UC6oDys1BGgBsIC3WhG1BovQ",
        "twitterId": "@ShizuRin23"
    },
    {
        "channelId": "UCyof-1Ko_jy2sOtivyTpc4Q",
        "twitterId": "@sanrio_news"
    },
    {
        "channelId": "UCARI2g7r-PHaxrIcAYsMfmA",
        "twitterId": "@azuma_lim"
    },
    {
        "channelId": "UCTMgd9qnUD9qKBX5oTtD6ug",
        "twitterId": "@virtual_obachan"
    },
    {
        "channelId": "UCwSOARsvB-Qa6PtuYyK74dA",
        "twitterId": "@rnqq"
    },
    {
        "channelId": "UCsg-YqdqQ-KFF0LNk23BY4A",
        "twitterId": "@HiguchiKaede"
    },
    {
        "channelId": "UCg8TPE5nLLOqlNnBivmQwww",
        "twitterId": "@MIYA_KIMINO"
    },
    {
        "channelId": "UCGaUWM5OQ7hU1JwbqvNBR4w",
        "twitterId": "@HatobaTsugu"
    },
    {
        "channelId": "UCAr7rLi_Wn09G-XfTA07d4g",
        "twitterId": "@kotonegami"
    },
    {
        "channelId": "UCGcD5iUDG8xiywZeeDxye-A",
        "twitterId": "@oda_nobuhime"
    },
    {
        "channelId": "UCw5MXcDMVg6oT69yfulq33Q",
        "twitterId": "@tanakayoshio815"
    },
    {
        "channelId": "UCBePKUYNhoMcjBi-BRmjarQ",
        "twitterId": "@Vtuber_Moe"
    },
    {
        "channelId": "UCmZA7XRRzmxhM4jPltZX1Zg",
        "twitterId": "@corona567ice"
    },
    {
        "channelId": "UCeAfiVvEuyICYJW-f3GnQjQ",
        "twitterId": "@Kerin_Vtuber"
    },
    {
        "channelId": "UC1pR2ig6NhndhvicEgclNdA",
        "twitterId": "@PinkyPopHepburn"
    },
    {
        "channelId": "UCDOJkSTUNY3_NKawpkPvjHg",
        "twitterId": "@aikatsu_dcd"
    },
    {
        "channelId": "UCIdEIHpS0TdkqRkHL5OkLtA",
        "twitterId": "@sana_natori"
    },
    {
        "channelId": "UC0g1AE0DOjBYnLhkgoRWN1w",
        "twitterId": "@honmahimawari"
    },
    {
        "channelId": "UCfFhyViosklD4kvyO-M0BJA",
        "twitterId": "@h_kanna_channel"
    },
    {
        "channelId": "UC4OeUf_KfYRrwksschtRYow",
        "twitterId": "@Kyo_Hanabasami"
    },
    {
        "channelId": "UCNjTjd2-PMC8Oo_-dCEss7A",
        "twitterId": "@omesis_ray"
    },
    {
        "channelId": "UCfiK42sBHraMBK6eNWtsy7A",
        "twitterId": "@kashikomari_ch"
    },
    {
        "channelId": "UCyZoDBhW8cLrzZ-dqKdQqEg",
        "twitterId": "@mayaputriid"
    },
    {
        "channelId": "UCt0clH12Xk1-Ej5PXKGfdPA",
        "twitterId": "@AliceMononobe"
    },
    {
        "channelId": "UC_4tXjqecqox5Uc05ncxpxg",
        "twitterId": "@yuika_siina"
    },
    {
        "channelId": "UCwokZsOK_uEre70XayaFnzA",
        "twitterId": "@suzukautako"
    },
    {
        "channelId": "UCoztvTULBYd3WmStqYeoHcA",
        "twitterId": "@saku_sasaki"
    },
    {
        "channelId": "UCz0lin3ZsOtmr2yuTN2MDQg",
        "twitterId": "@beilene191969"
    },
    {
        "channelId": "UCYKP16oMX9KKPbrNgo_Kgag",
        "twitterId": "@Elu_World"
    },
    {
        "channelId": "UCM2SwvNjA0uH8oc5D0ihSDA",
        "twitterId": "@takao_shinji"
    },
    {
        "channelId": "UCeLzT-7b2PBcunJplmWtoDg",
        "twitterId": "@Patra_HNST"
    },
    {
        "channelId": "UCdn5BQ06XqgXoAxIhbqw5Rg",
        "twitterId": "@shirakamifubuki"
    },
    {
        "channelId": "UCz6Gi81kE6p5cdW1rT0ixqw",
        "twitterId": "@mokomeme_ch"
    },
    {
        "channelId": "UCv1fFr156jc65EMiLbaLImw",
        "twitterId": "@rei_Toya_rei"
    },
    {
        "channelId": "UCErkC29SJY8RGSpIJa9qJoA",
        "twitterId": "@ibakira_Vtuber"
    },
    {
        "channelId": "UC1zFJrfEKvCixhsjNSb1toQ",
        "twitterId": "@SisterCleaire"
    },
    {
        "channelId": "UC6TyfKcsrPwBsBnx2QobVLQ",
        "twitterId": "@BAyoutuber"
    },
    {
        "channelId": "UC8NZiqKx6fsDT3AVcMiVFyA",
        "twitterId": "@norioo_"
    },
    {
        "channelId": "UC_GCs6GARLxEHxy1w40d6VQ",
        "twitterId": "@ienaga_mugi23"
    },
    {
        "channelId": "UCX7YkU9nEeaoZbkVLVajcMg",
        "twitterId": "@nijisanji_app"
    },
    {
        "channelId": "UCLO9QDxVL4bnvRRsz6K4bsQ",
        "twitterId": "@Chihiro_yuki23"
    },
    {
        "channelId": "UCDVXivWK9feX2iRBc3SFegw",
        "twitterId": "@minai_karte"
    },
    {
        "channelId": "UCXzcu59Cbu-hkpNNXnNiKDg",
        "twitterId": "@lesupo_ru321id"
    },
    {
        "channelId": "UCDqI2jOz0weumE8s7paEk6g",
        "twitterId": "@robocosan"
    },
    {
        "channelId": "UCmUjjW5zF1MMOhYUwwwQv9Q",
        "twitterId": "@ushimi_ichigo"
    },
    {
        "channelId": "UC3iwL9Yz8LcKkJsnLPevOTQ",
        "twitterId": "@VR_Girl_NoraCat"
    },
    {
        "channelId": "UCspv01oxUFf_MTSipURRhkA",
        "twitterId": "@Kanae_2434"
    },
    {
        "channelId": "UCvmppcdYf4HOv-tFQhHHJMA",
        "twitterId": "@Moiramoimoimoi"
    },
    {
        "channelId": "UCPvGypSgfDkVe7JG2KygK7A",
        "twitterId": "@RindouMikoto"
    },
    {
        "channelId": "UCmgWMQkenFc72QnYkdxdoKA",
        "twitterId": "@osyarenuts"
    },
    {
        "channelId": "UCIqbU97D5CrknKaNik10A-A",
        "twitterId": "@Hackadoll"
    },
    {
        "channelId": "UCiGcHHHT3kBB1IGOrv7f3qQ",
        "twitterId": "@KongoIroha"
    },
    {
        "channelId": "UC1suqwovbL1kzsoaZgFZLKg",
        "twitterId": "@yuzukichococh"
    },
    {
        "channelId": "UCtpB6Bvhs1Um93ziEDACQ8g",
        "twitterId": "@KazakiMorinaka"
    },
    {
        "channelId": "UC0Owc36U9lOyi9Gx9Ic-4qg",
        "twitterId": "@Haneru_Inaba"
    },
    {
        "channelId": "UCwRKt_raV3N5KZgxcFyC1vw",
        "twitterId": "@suntory_nomu"
    },
    {
        "channelId": "UCXLqxLD5qCsWC1iEdE-rsWg",
        "twitterId": "@EvEch_xxx"
    },
    {
        "channelId": "UCOefINa2_BmpuX4BbHjdk9A",
        "twitterId": "@YozakuraTama"
    },
    {
        "channelId": "UC1EB8moGYdkoZQfWHjh7Ivw",
        "twitterId": "@ponpokoka"
    },
    {
        "channelId": "UC_zztIHGbBz9L-ZM-Ta2O1Q",
        "twitterId": "@yua_ch"
    },
    {
        "channelId": "UCPLeqi7rIqS9uY4_TrSUOMg",
        "twitterId": "@tamako_aogiri"
    },
    {
        "channelId": "UCk-m-OXRVEXUolSWtmY56oA",
        "twitterId": "@mansayadadada"
    },
    {
        "channelId": "UCV5ZZlLjk5MKGg3L0n0vbzw",
        "twitterId": "@TakamiyaRion"
    },
    {
        "channelId": "UC5nfcGkOAm3JwfPvJvzplHg",
        "twitterId": "@KitakamiFutaba"
    },
    {
        "channelId": "UCzrw4K7D9Ti3FP8WMTVPImg",
        "twitterId": "@TypeA_Airi"
    },
    {
        "channelId": "UC53UDnhAAYwvNO7j_2Ju1cQ",
        "twitterId": "@___Dola"
    },
    {
        "channelId": "UCSgheR9xOIcQjlkeXqIofLQ",
        "twitterId": "@D_W_Underground"
    },
    {
        "channelId": "UCt5-0i4AVHXaWJrL8Wql3mw",
        "twitterId": "@midori_2434"
    },
    {
        "channelId": "UCSFCh5NL4qXrAy9u-u2lX3g",
        "twitterId": "@Vamp_Kuzu"
    },
    {
        "channelId": "UCf3DHSmd2DhZcoq2gwYXCIA",
        "twitterId": "@RukiRoki_ch"
    },
    {
        "channelId": "UCP9ZgeIJ3Ri9En69R0kJc9Q",
        "twitterId": "@chieri_kakyoin"
    },
    {
        "channelId": "UCbc8fwhdUNlqi-J99ISYu4A",
        "twitterId": "@belmond_b_2434"
    },
    {
        "channelId": "UChUJbHiTVeGrSkTdBzVfNCQ",
        "twitterId": "@JoeRikiichi"
    },
    {
        "channelId": "UC4rQ3kXJGDV8sx6oZK8apEA",
        "twitterId": "@_seren_di"
    },
    {
        "channelId": "UCO6i768QTqAmGeV-iqZU2pg",
        "twitterId": "@BitYoutube"
    },
    {
        "channelId": "UCNUgrFCo2Hr_VXc9bEwjcHQ",
        "twitterId": "@_rnrrdark"
    },
    {
        "channelId": "UC2Rr7mILebYLTjd38DNNUTw",
        "twitterId": "@fairyschan"
    },
    {
        "channelId": "UCwePpiw1ocZRSNSkpKvVISw",
        "twitterId": "@Mary_HNST"
    },
    {
        "channelId": "UCKMYISTJAQ8xTplUPHiABlA",
        "twitterId": "@846kizuQ"
    },
    {
        "channelId": "UCtYSNR3w7_31Kx76e9XmVEw",
        "twitterId": "@SentanKyofusho"
    },
    {
        "channelId": "UCt9qik4Z-_J-rj3bKKQCeHg",
        "twitterId": "@aki_suzuya"
    },
    {
        "channelId": "UC8v7P8Bs1QPmfF8Cp5HqQhw",
        "twitterId": "@vjpofficial"
    },
    {
        "channelId": "UCkPVMV6rbgfB7FO0IKpsNAg",
        "twitterId": "@ginjoshimai"
    },
    {
        "channelId": "UCfM_A7lE6LkGrzx6_mOtI4g",
        "twitterId": "@setsuna2434"
    },
    {
        "channelId": "UCMzxQ58QL4NNbWghGymtHvw",
        "twitterId": "@carro_pino"
    },
    {
        "channelId": "UCBi8YaVyZpiKWN3_Z0dCTfQ",
        "twitterId": "@Youko_Akabane"
    },
    {
        "channelId": "UCfxUC1e8kStZYNNc7xQuxag",
        "twitterId": "@sonico_macaron"
    },
    {
        "channelId": "UC3UKMRQmBcjXWu66cvxcngA",
        "twitterId": "@Eli_HNST"
    },
    {
        "channelId": "UCeK9HFcRZoTrvqcUCtccMoQ",
        "twitterId": "@sibuya_hajime"
    },
    {
        "channelId": "UChqYnJlFxlBi6DfRz6jRenQ",
        "twitterId": "@Hinako_Umori"
    },
    {
        "channelId": "UCp77Qho-YHhnklRr-DkjiOw",
        "twitterId": "@nijikawa_laki"
    },
    {
        "channelId": "UCsFn_ueskBkMCEyzCEqAOvg",
        "twitterId": "@ZulmIhP1nlMOT5y"
    },
    {
        "channelId": "UC48jH1ul-6HOrcSSfoR02fQ",
        "twitterId": "@Yuuhi_Riri"
    },
    {
        "channelId": "UCobEOOm5RDIupAg5bpZ31Dg",
        "twitterId": "@yume_ui"
    },
    {
        "channelId": "UCNPu5zXzXvS6pLCCaI5SnSA",
        "twitterId": "@Kurorin_V"
    },
    {
        "channelId": "UCPljC4d-GgdFgVqtoCZ3m_w",
        "twitterId": "@poteti_oekaki"
    },
    {
        "channelId": "UCv5yMCWzjt5w_1czERqYkvQ",
        "twitterId": "@overlord_ch"
    },
    {
        "channelId": "UCUZ5AlC3rTlM-rA2cj5RP6w",
        "twitterId": "@kagura_suzu"
    },
    {
        "channelId": "UC02LBsjt_Ehe7k0CuiNC6RQ",
        "twitterId": "@nekonoki_mochi"
    },
    {
        "channelId": "UC2hA-6M66dE2Tt_4xM8K9wQ",
        "twitterId": "@Gorilla_Virtual"
    },
    {
        "channelId": "UCPf-EnX70UM7jqjKwhDmS8g",
        "twitterId": "@ukyo_rst"
    },
    {
        "channelId": "UCCVwhI5trmaSxfcze_Ovzfw",
        "twitterId": "@yuzuki_roa"
    },
    {
        "channelId": "UCZ1WJDkMNiZ_QwHnNrVf7Pw",
        "twitterId": "@mochi8hiyoko"
    },
    {
        "channelId": "UC1519-d1jzGiL1MPTxEdtSA",
        "twitterId": "@YaezawaNatori"
    },
    {
        "channelId": "UC8QEgcJgjrJWy4B43aXxsAQ",
        "twitterId": "@Ninja_Inui"
    },
    {
        "channelId": "UCP19rQ5V-46B-6ZeLDJqp5w",
        "twitterId": "@debidebiru_sama"
    },
    {
        "channelId": "UCJubINhCcFXlsBwnHp0wl_g",
        "twitterId": "@maimoto_k"
    },
    {
        "channelId": "UCyb-cllCkMREr9de-hoiDrg",
        "twitterId": "@YamatoIori"
    },
    {
        "channelId": "UC7-N7MvN5muVIHqyQx9LFbA",
        "twitterId": "@makeagames2018"
    },
    {
        "channelId": "UCZYyhgoV314CM14zBD6vd4A",
        "twitterId": "@tenkaitukasa"
    },
    {
        "channelId": "UC1CfXB_kRs3C-zaeTG3oGyg",
        "twitterId": "@akaihaato"
    },
    {
        "channelId": "UCXU7YYxy_iQd3ulXyO-zC2w",
        "twitterId": "@gaku_fushimi"
    },
    {
        "channelId": "UCWCc8tO-uUl_7SJXIKJACMw",
        "twitterId": "@Freeze_Mea"
    },
    {
        "channelId": "UCKUcnaLsG2DeQqza8zRXHiA",
        "twitterId": "@UshimakiRiko"
    },
    {
        "channelId": "UCeShTCVgZyq2lsBW9QwIJcw",
        "twitterId": "@g9v9g_mirei"
    },
    {
        "channelId": "UCBiqkFJljoxAj10SoP2w2Cg",
        "twitterId": "@nekokan_chu"
    },
    {
        "channelId": "UChT4jRjRUhFSrDT6fjzsHFw",
        "twitterId": "@strk_tenshi"
    },
    {
        "channelId": "UC9EjSJ8pvxtvPdxLOElv73w",
        "twitterId": "@makaino_ririmu"
    },
    {
        "channelId": "UCODNLyn3L83wEmC0DLL0cxA",
        "twitterId": "@asanohikariunei"
    },
    {
        "channelId": "UCLaGi3DhbdSML4QE-7dI0LQ",
        "twitterId": "@chokyosyojo"
    },
    {
        "channelId": "UC84RYorF7UcJzt_iAYXBisA",
        "twitterId": "@lara_songs"
    },
    {
        "channelId": "UCqeY0fp1IBDJW58HwZBh1Lw",
        "twitterId": "@okashinoram"
    },
    {
        "channelId": "UCmM5LprTu6-mSlIiRNkiXYg",
        "twitterId": "@KisoAzuki"
    },
    {
        "channelId": "UCP2o-o6u4uX3uq1hXspl0rg",
        "twitterId": "@kudou_chitose"
    },
    {
        "channelId": "UCRMpIxnySp7Fy5SbZ8dBv2w",
        "twitterId": "@kmnzliz"
    },
    {
        "channelId": "UCwuS0uY-Z2Gr_5OV2oFybFA",
        "twitterId": "@kmnzlita"
    },
    {
        "channelId": "UCwndlbPCkOTT9u03CKH9Kew",
        "twitterId": "@shiromakumach"
    },
    {
        "channelId": "UCNwo7eikmX5HPs7NedWVBgw",
        "twitterId": "@hibiki_ao"
    },
    {
        "channelId": "UCqEp6RdtsMbUNrCdCswr6pA",
        "twitterId": "@god_yaksa23"
    },
    {
        "channelId": "UCQ1U65-CQdIoZ2_NA4Z4F7A",
        "twitterId": "@virtual_kaf"
    },
    {
        "channelId": "UC1opHUrw8rvnsadT-iGp7Cg",
        "twitterId": "@minatoaqua"
    },
    {
        "channelId": "UC9UzocR-pBvUx7P9owdlqJw",
        "twitterId": "@amakawaalto"
    },
    {
        "channelId": "UCtsGKowrX5oz5CIUB2vdH0g",
        "twitterId": "@buddyfight"
    },
    {
        "channelId": "UCmNjDc-wW_nqs4WzEHKyJnw",
        "twitterId": "@pj_tokyodolls"
    },
    {
        "channelId": "UCDh2bWI5EDu7PavqwICkVpA",
        "twitterId": "@Mico_HNST"
    },
    {
        "channelId": "UC0TXe_LYZ4scaW2XMyi5_kw",
        "twitterId": "@AZKi_VDiVA"
    },
    {
        "channelId": "UCMaXopOC-gQ_NFTkq7esf4w",
        "twitterId": "@maguraene"
    },
    {
        "channelId": "UC5pQ407lVd4Rf0Y6GilXdwg",
        "twitterId": "@yuyamilukia"
    },
    {
        "channelId": "UC16P6nSFhimmcjQKrdOx2IQ",
        "twitterId": "@setoya0102"
    },
    {
        "channelId": "UCwalpGCurSDqwSpkAR4h6LA",
        "twitterId": "@_fujimasakura"
    },
    {
        "channelId": "UCNA0XC_zxS63d4Q-JMIMyug",
        "twitterId": "@megu_shinonome"
    },
    {
        "channelId": "UCveZ9Ic1VtcXbsyaBgxPMvg",
        "twitterId": "@warabeda_meiji"
    },
    {
        "channelId": "UCAWxPGGuIfWME2KTLUmSCHw",
        "twitterId": "@pakatube"
    },
    {
        "channelId": "UCtnWqAC7UxKlKSo2GSvxBJw",
        "twitterId": "@taigayuu"
    },
    {
        "channelId": "UCmeyo5pRj_6PXG-CsGUuWWg",
        "twitterId": "@BlackShiba_chan"
    },
    {
        "channelId": "UCUzJ90o1EjqUbk2pBAy0_aw",
        "twitterId": "@Gilzaren_III"
    },
    {
        "channelId": "UCKgndddKiQGIn0-T8jHzndg",
        "twitterId": "@ame_no_sei"
    },
    {
        "channelId": "UCYTz3uIgwVY3ZU-IQJS8r3A",
        "twitterId": "@Charlotte_HNST"
    },
    {
        "channelId": "UCksFV3h5Jm5BWNCN4BBej2A",
        "twitterId": "@kameyama66"
    },
    {
        "channelId": "UCL-2thbJ7grC9fmGF4OLuTg",
        "twitterId": "@camomi_camomi"
    },
    {
        "channelId": "UC3lNFeJiTq6L3UWoz4g1e-A",
        "twitterId": "@udukikohh"
    },
    {
        "channelId": "UCcfEPfRcoJrBDmz_E3wHJuA",
        "twitterId": "@nemumineruch"
    },
    {
        "channelId": "UCvzGlP9oQwU--Y0r9id_jnA",
        "twitterId": "@oozorasubaru"
    },
    {
        "channelId": "UCc5BawFmb7aNHck7HFtSKvw",
        "twitterId": "@hiyatoireiko"
    },
    {
        "channelId": "UCzhwXcK9DTiY-VqYjwnjZhQ",
        "twitterId": "@magical_matsuri"
    },
    {
        "channelId": "UCth5j6WaPTf9osdNrdz92PA",
        "twitterId": "@Ame_Soyokaze"
    },
    {
        "channelId": "UCFqfJ43vR3lcF2PGZfN25qQ",
        "twitterId": "@watako_popokids"
    },
    {
        "channelId": "UCfF_5NnmiX9MALwrIxCu2ow",
        "twitterId": "@misaki_nonaka"
    },
    {
        "channelId": "UCFI81W9F49a7GvimKF905eQ",
        "twitterId": "@rbc_geino"
    },
    {
        "channelId": "UCI-xaXiiRD_2l8qxQRIpeEw",
        "twitterId": "@kakyoin_tsubaki"
    },
    {
        "channelId": "UCiVRnULJjc8o-j_lG5BAzKw",
        "twitterId": "@cafenozombiko"
    },
    {
        "channelId": "UC2kyQhzGOB-JPgcQX9OMgEw",
        "twitterId": "@Ichika_Souya"
    },
    {
        "channelId": "UChu8Yu_w9z8DGFtXzuGvDlg",
        "twitterId": "@jashinchan_PJ"
    },
    {
        "channelId": "UCk0dNVAdlgn4ynURwAq_z2A",
        "twitterId": "@todoki_uka"
    },
    {
        "channelId": "UCB1s_IdO-r0nUkY2mXeti-A",
        "twitterId": "@LeonaShishigami"
    },
    {
        "channelId": "UCD8HOxPs4Xvsm8H0ZxXGiBw",
        "twitterId": "@yozoramel"
    },
    {
        "channelId": "UCSv-TsF2gkYAMr6p29Os7Hg",
        "twitterId": "@_nugum"
    },
    {
        "channelId": "UCQ0UDLQCjY0rmuxCDE38FGg",
        "twitterId": "@natsuiromatsuri"
    },
    {
        "channelId": "UCyGj6V3bfgYr191geObqdow",
        "twitterId": "@Miria_channel27"
    },
    {
        "channelId": "UCT1AQFit-Eaj_YQMsfV0RhQ",
        "twitterId": "@alice_shinryaku"
    },
    {
        "channelId": "UCPH7d3YxfeH56FG-UyPAB1g",
        "twitterId": "@A_BOX_LAND"
    },
    {
        "channelId": "UCxDWDV3jbTLSOVWYVjo1_Nw",
        "twitterId": "@mimitaro_vt"
    },
    {
        "channelId": "UCuPrcSmgo6twlAQzwYPlSkQ",
        "twitterId": "@nano_phan"
    },
    {
        "channelId": "UCl-3q6t6zdZwgIsFZELb7Zg",
        "twitterId": "@SRYR_0"
    },
    {
        "channelId": "UCFJmvu4Dho2ji_CZtUcvrJw",
        "twitterId": "@reiko_housewife"
    },
    {
        "channelId": "UCRvpMpzAXBRKJQuk-8-Sdvg",
        "twitterId": "@Ran_Hinokuma"
    },
    {
        "channelId": "UCXTpFs_3PqI41qX2d9tL2Rw",
        "twitterId": "@murasakishionch"
    },
    {
        "channelId": "UCvy86WpnHG-h7-tgBVQBJYg",
        "twitterId": "@nidaimeaka"
    },
    {
        "channelId": "UCGiFzwdasSAHILrx-DB1pVQ",
        "twitterId": "@Kuromu_Inari"
    },
    {
        "channelId": "UCLpYMk5h1bq8_GAFVBgXhPQ",
        "twitterId": "@ikasumi_zzz"
    },
    {
        "channelId": "UCCRZH38F6BkexM6edXkwG8g",
        "twitterId": "@mikuriya_9on"
    },
    {
        "channelId": "UCp-5t9SrOQwXMU7iIjQfARg",
        "twitterId": "@ookamimio"
    },
    {
        "channelId": "UC7fk0CB07ly8oSl0aqKkqFg",
        "twitterId": "@nakiriayame"
    },
    {
        "channelId": "UCwXOUuxUxCJ1yD0JfogUvMg",
        "twitterId": "@az_yukimi"
    },
    {
        "channelId": "UC0AnrsIjJ7BWl9xPy_nWUZA",
        "twitterId": "@Iaughing_fox"
    },
    {
        "channelId": "UCkD-wlU06zeiGSk31y2qIOw",
        "twitterId": "@SIROyoutuber"
    },
    {
        "channelId": "UCLXxry0HqEz_mzHSsXwrhYg",
        "twitterId": "@mitukineu"
    },
    {
        "channelId": "UCc04WdXUKAMY_Sh3Y7B0Vxg",
        "twitterId": "@TEN_1203"
    },
    {
        "channelId": "UCks41vQN-hN-1KHmpZyPY3A",
        "twitterId": "@azuma_dazo"
    },
    {
        "channelId": "UC7IZJI6cjoFnF3YGuKfieBg",
        "twitterId": "@sumomo_hiiro"
    },
    {
        "channelId": "UCfQVs_KuXeNAlGa3fb8rlnQ",
        "twitterId": "@SAKURA_RITSUKI"
    },
    {
        "channelId": "UCH4yRBPH2pDUjPeqomx8CTQ",
        "twitterId": "@teruto_nico"
    },
    {
        "channelId": "UCDG8K9g6qo8gX4jCjsqUVzA",
        "twitterId": "@monsterzmate"
    },
    {
        "channelId": "UCFaDvgez8USXHiKidt0NtZg",
        "twitterId": "@839yuzu"
    },
    {
        "channelId": "UCuGMkxJA_icuiF01u8f3Y2Q",
        "twitterId": "@HeroMinamori"
    },
    {
        "channelId": "UCg49h2KFnB3SH1efaI_njVg",
        "twitterId": "@tiyu12sai"
    },
    {
        "channelId": "UCynHwUYnx8V0NJ9_pU-aAsA",
        "twitterId": "@sahana_virtual"
    },
    {
        "channelId": "UCfzSiAfER51yIWY92YcrAXA",
        "twitterId": "@YuyuVduelist"
    },
    {
        "channelId": "UCRV9d6YCYIMUszK-83TwxVA",
        "twitterId": "@KT_seeds"
    },
    {
        "channelId": "UCsA8nM8e5--IdeRaxZwTWHg",
        "twitterId": "@AkatsukiUNI"
    },
    {
        "channelId": "UCo7TRj3cS-f_1D9ZDmuTsjw",
        "twitterId": "@chima_machita23"
    },
    {
        "channelId": "UC_AuJsYVZTfYO2LF1PDTuTA",
        "twitterId": "@nyanko_chikuwa"
    },
    {
        "channelId": "UCZx7wgGNs2UFyRRtLoNur9Q",
        "twitterId": "@osanai_mei"
    },
    {
        "channelId": "UCHccxX2p_9DB_HPnXSb2omw",
        "twitterId": "@kasukaBe_nyoki"
    },
    {
        "channelId": "UCCsZjHDiCgvlZ8VyCQMEYuQ",
        "twitterId": "@VT_212"
    },
    {
        "channelId": "UCHXgFLFyqR-XqtxfTH3qiYA",
        "twitterId": "@mao_DBmiyuki"
    },
    {
        "channelId": "UCvGW3NYU2kokJZcS4wVvk6g",
        "twitterId": "@ezweb_dylan"
    },
    {
        "channelId": "UCVFpIqGoTmFaoMmyFPRYrKA",
        "twitterId": "@Mizushina_Aoi"
    },
    {
        "channelId": "UCufQu4q65z63IgE4cfKs1BQ",
        "twitterId": "@KataribeTsumugu"
    },
    {
        "channelId": "UC5WJgKelM1YO3AsXtR-t4SQ",
        "twitterId": "@osanazu_FKG"
    },
    {
        "channelId": "UCTIE7LM5X15NVugV7Krp9Hw",
        "twitterId": "@kakeru_yumeoi"
    },
    {
        "channelId": "UC_4SADjnjt22NO-fTFN6prQ",
        "twitterId": "@saki_Ouga"
    },
    {
        "channelId": "UCVbTY60cxU22hzyetbt5lMA",
        "twitterId": "@Jinbey_Aoyama"
    },
    {
        "channelId": "UCstBOFri42BL70MswRQG3uw",
        "twitterId": "@o_sui_sui_"
    },
    {
        "channelId": "UCkPIfBOLoO0hVPG-tI2YeGg",
        "twitterId": "@tomari_mari"
    },
    {
        "channelId": "UCuz0vzQgC8LRdS6lVV0UkUg",
        "twitterId": "@ac1kt"
    },
    {
        "channelId": "UCIqfGSGcz_q7zkZYlmU04GQ",
        "twitterId": "@a_okome_channel"
    },
    {
        "channelId": "UCaF-mODqAziHivqg0Q61XKQ",
        "twitterId": "@Darkness_Eater"
    },
    {
        "channelId": "UCQG5eRfno9f2rptcM6srQZA",
        "twitterId": "@ileheart_ch"
    },
    {
        "channelId": "UC6TfqY40Xt1Y0J-N18c85qQ",
        "twitterId": "@momo_aduchi"
    },
    {
        "channelId": "UC2jBqh7fCEPuTdpwKmxHvjA",
        "twitterId": "@umakoshi_dream"
    },
    {
        "channelId": "UCiSRx1a2k-0tOg-fs6gAolQ",
        "twitterId": "@hina__asuka"
    },
    {
        "channelId": "UCsQtQKuQCIg_1BwRZubb_pg",
        "twitterId": "@pipipipipi_wara"
    },
    {
        "channelId": "UCctWfjgLUh1yt-Wdz6W4yFQ",
        "twitterId": "@Misositaworks"
    },
    {
        "channelId": "UCFTLzh12_nrtzqBPsTCqenA",
        "twitterId": "@akirosenthal"
    },
    {
        "channelId": "UCmNDDyZYRnmuhY-HVF7C54Q",
        "twitterId": "@ZX_Tech_"
    },
    {
        "channelId": "UCuwpvDAYMV0nV98DQk-W9mQ",
        "twitterId": "@MitsuHanano"
    },
    {
        "channelId": "UC7IyAJq03ohb0TpGqsFfPng",
        "twitterId": "@hiramecurry"
    },
    {
        "channelId": "UCRWOdwLRsenx2jLaiCAIU4A",
        "twitterId": "@Sayo_Amemori"
    },
    {
        "channelId": "UCnDZwUFMzqOBcF3bjRfZD-g",
        "twitterId": "@rohto_cocoro"
    },
    {
        "channelId": "UC6s0wLR0TZauzTVoGGw2r6g",
        "twitterId": "@hooniefriends"
    },
    {
        "channelId": "UCPMTymbIaaR93V47LvCBxzA",
        "twitterId": "@ARuKo_OKaRa"
    },
    {
        "channelId": "UCo5uTjnUikW0giyrKOIrOQA",
        "twitterId": "@n_sisi_channel"
    },
    {
        "channelId": "UCf97Z6Ntd1n0LQ3TsUtYNgQ",
        "twitterId": "@rokudo_mei"
    },
    {
        "channelId": "UCWz0CSYCxf4MhRKPDm220AQ",
        "twitterId": "@Kanda_Shoichi"
    },
    {
        "channelId": "UC2xrDXTlTyxagWiMNWTk6nA",
        "twitterId": "@meiden_ryusei"
    },
    {
        "channelId": "UCfLsVuE0A_hUQyeCDNQelxA",
        "twitterId": "@neeko_tsurai"
    },
    {
        "channelId": "UCs4zWdCrlnXmpVkjOgAHs0w",
        "twitterId": "@mid_midy"
    },
    {
        "channelId": "UC8g5_Cua_Q8dkrbRl4uDEkQ",
        "twitterId": "@himono_vtuber"
    },
    {
        "channelId": "UC959pG-mQNdwu0kOMHp9AmQ",
        "twitterId": "@zizio413"
    },
    {
        "channelId": "UCxp-_zVZcJBwZzjLt-LwAaQ",
        "twitterId": "@matsuri_kzmy"
    },
    {
        "channelId": "UCDA4f1tItU3RaZgYxMInz4w",
        "twitterId": "@Reiden_Kasuka"
    },
    {
        "channelId": "UCjKvR591Lk-izSv9zKSpP-g",
        "twitterId": "@KaminariAi"
    },
    {
        "channelId": "UCu5DbFfYe3KiwhcmanCvSVg",
        "twitterId": "@pandei_ch"
    },
    {
        "channelId": "UC9vyQt8JlsI8IvLRCtDjp-w",
        "twitterId": "@xuniDD"
    },
    {
        "channelId": "UCQ7j4vwUIxsXtETjMFZ8-SQ",
        "twitterId": "@nao_2574"
    },
    {
        "channelId": "UC_tw32N5PtFofQXmEoAufmw",
        "twitterId": "@cecilia4696"
    },
    {
        "channelId": "UCgwDRo9v_eMMFXgvctbdOjg",
        "twitterId": "@VTM_himari"
    },
    {
        "channelId": "UCHK5wkevfaGrPr7j3g56Jmw",
        "twitterId": "@seto_miyako"
    },
    {
        "channelId": "UChLfthKoUV502J7gU9STArg",
        "twitterId": "@ShibuyaHAL"
    },
    {
        "channelId": "UCL9dLCVvHyMiqjp2RDgowqQ",
        "twitterId": "@re2_takatsuki"
    },
    {
        "channelId": "UChGY3OpdU6wzFzygJ_Rjvlw",
        "twitterId": "@Eve_scp"
    },
    {
        "channelId": "UCmqrvfLMws-GLGHQcB5dasg",
        "twitterId": "@_kanade_kanon"
    },
    {
        "channelId": "UCuE6xoui7gZOTUiF0OtWWJw",
        "twitterId": "@asahi_ych"
    },
    {
        "channelId": "UCg63a3lk6PNeWhVvMRM_mrQ",
        "twitterId": "@onomachi_haruka"
    },
    {
        "channelId": "UCs_aRmEvwiMZQlVGAXV-8Iw",
        "twitterId": "@harukasora_info"
    },
    {
        "channelId": "UCM69L73KZwo__gte8Bhghcw",
        "twitterId": "@edielec"
    },
    {
        "channelId": "UC-hM6YJuNYVAmUWxeIr9FeA",
        "twitterId": "@sakuramiko35"
    },
    {
        "channelId": "UCLl6SoIaxp3cZQZ6g7jeMaA",
        "twitterId": "@suzuhatachibana"
    },
    {
        "channelId": "UCfd70dsHfx0vevwIoUv3zCw",
        "twitterId": "@bkeygames"
    },
    {
        "channelId": "UCcVn0OiL4isLZfa_WWelLyQ",
        "twitterId": "@yamai_kokoro"
    },
    {
        "channelId": "UCGFD_8TRHhlpjfqGhLUSk4g",
        "twitterId": "@Vtuber_Icotsu"
    },
    {
        "channelId": "UC-UmUsocuVAxsKog3QonhpA",
        "twitterId": "@TamaneUta"
    },
    {
        "channelId": "UCKDHdDpoE9lurDuyAGAuNnw",
        "twitterId": "@neko_vtuber"
    },
    {
        "channelId": "UC_9nmotxi7FAfiJpo1RKy8A",
        "twitterId": "@maaru_witch"
    },
    {
        "channelId": "UCUxazE0cXa92LNa-UjqlxDQ",
        "twitterId": "@85_85ch"
    },
    {
        "channelId": "UCKB7wj18jCUTGcwmiGY0V-Q",
        "twitterId": "@RyukiM426"
    },
    {
        "channelId": "UCfeKtb0E5lBKIkAGlzzoZdA",
        "twitterId": "@cookpad_pr"
    },
    {
        "channelId": "UCk7UMlCJ6dlluad9GLKhHzg",
        "twitterId": "@tiatiach"
    },
    {
        "channelId": "UCju7v8SkoWUQ5ITCQwmYpYg",
        "twitterId": "@milk_merry_"
    },
    {
        "channelId": "UCn14Z641OthNps7vppBvZFA",
        "twitterId": "@hanachigusa_ch"
    },
    {
        "channelId": "UCRULMVtTfuMRRBAzfaqYwdA",
        "twitterId": "@DJ_FOX_JAPAN"
    },
    {
        "channelId": "UCvzVB-EYuHFXHZrObB8a_Og",
        "twitterId": "@Rine_Yaguruma"
    },
    {
        "channelId": "UCqQV8xEBWd5SVZBLlYrS_5Q",
        "twitterId": "@tukimi_sizuku"
    },
    {
        "channelId": "UCiqHlJh_i0z3PUadvlcWpEg",
        "twitterId": "@7se_taku"
    },
    {
        "channelId": "UCm_rSqgU2lFfjU1rn-uqbXA",
        "twitterId": "@pagemi_v"
    },
    {
        "channelId": "UCn75BLMKpV8w0uH8JcfilWQ",
        "twitterId": "@niiiiiina1215"
    },
    {
        "channelId": "UC7xyzq_Hd72-IbJVoz4DSrQ",
        "twitterId": "@nemchan_nel"
    },
    {
        "channelId": "UCZF1cUKuWlvo_wn--s-21kw",
        "twitterId": "@hinari_Amls"
    },
    {
        "channelId": "UCtAvQ5U0aXyKwm2i4GqFgJg",
        "twitterId": "@harusakiair2434"
    },
    {
        "channelId": "UC2zuO8mkXTI5l-s6TL7uzuw",
        "twitterId": "@shiroken_2900"
    },
    {
        "channelId": "UCDPdK4ftX-GOWrWHtM4UMZw",
        "twitterId": "@Tia_Ushio"
    },
    {
        "channelId": "UCBe_jjkUHhVNAj46bukAbJA",
        "twitterId": "@miyuri_koto"
    },
    {
        "channelId": "UCupCAZz1l52vV8m-dvaoBVQ",
        "twitterId": "@CierraRunis"
    },
    {
        "channelId": "UCix1ZTZthK4ndo5WVVr4vUg",
        "twitterId": "@Yotsuya_Pro"
    },
    {
        "channelId": "UCXJQy1CifhBme9kOM6eWlGg",
        "twitterId": "@kogeinu"
    },
    {
        "channelId": "UCX2Sm8SGWTUOyCizgrzadXA",
        "twitterId": "@uta_kirahoshi"
    },
    {
        "channelId": "UCKC8DnXhht8zj7VQVWsXlIw",
        "twitterId": "@itallinc"
    },
    {
        "channelId": "UCGCb4Dts1uYtciya3wvd6dg",
        "twitterId": "@iwataiki"
    },
    {
        "channelId": "UC9S88PESIt-gDZvAS-Kt6-Q",
        "twitterId": "@RARA_fh"
    },
    {
        "channelId": "UCH0ObmokE-zUOeihkKwWySA",
        "twitterId": "@Yumeno_Shiori"
    },
    {
        "channelId": "UC4NiGZqQQvpvNvwcJsm_EAg",
        "twitterId": "@vroadcaster"
    },
    {
        "channelId": "UCQn11OvxTnBMCPINvDcl4Wg",
        "twitterId": "@hatyati"
    },
    {
        "channelId": "UC2JMXD8btPtvJafM3dawF-Q",
        "twitterId": "@yrn__tbr"
    },
    {
        "channelId": "UCHb8IFQ1xGZTmt2rygOw3tw",
        "twitterId": "@dot_alicechan"
    },
    {
        "channelId": "UCendfm780DgZophhZyo6xnQ",
        "twitterId": "@koo_fran_zopar"
    },
    {
        "channelId": "UCM-huGRkWiBmAdaOCPxhjCQ",
        "twitterId": "@sega_idola"
    },
    {
        "channelId": "UCX7WYPXASkYUm2GyomLllIg",
        "twitterId": "@Moscow_ojisan"
    },
    {
        "channelId": "UCH8Au-zDgE7ha2Y0IwaRsEQ",
        "twitterId": "@3Dkanojo_anime"
    },
    {
        "channelId": "UC1EsupKhsMNuw7InGoSnKdA",
        "twitterId": "@shinkukandolls"
    },
    {
        "channelId": "UCdnOBt0-J4L843mBKIKxsmg",
        "twitterId": "@tamaki_ukon"
    },
    {
        "channelId": "UCBXEcW0gRiTARStvlgR1L9A",
        "twitterId": "@Usamoto_Anna"
    },
    {
        "channelId": "UCup2TSNKxDM_SNCF9xuXSNg",
        "twitterId": "@moni_yoshimochi"
    },
    {
        "channelId": "UCFrH3bfn7gDeV29wrHHM80g",
        "twitterId": "@matoi_inuki"
    },
    {
        "channelId": "UC8UZk3EE_LPxWNyQ7RUDCYA",
        "twitterId": "@AirontheString"
    },
    {
        "channelId": "UCdvYw1B1EaOZfgO7-Ir3ORQ",
        "twitterId": "@tsumugi_kurama"
    },
    {
        "channelId": "UCl1yB_o-K9L3pJApyaeS2sg",
        "twitterId": "@Athena_psyidol"
    },
    {
        "channelId": "UCtRCF2NLRULCmf-oLAF455w",
        "twitterId": "@BUSON2025"
    },
    {
        "channelId": "UC03JcHIRnScf0_f8DScj3bw",
        "twitterId": "@tabehoJ"
    },
    {
        "channelId": "UC9E41LwRtQ2rFyNH3XsH3kQ",
        "twitterId": "@_satoreika"
    },
    {
        "channelId": "UC_E8Gdj0G_JCw61VFjG5qLg",
        "twitterId": "@takajin_ch"
    },
    {
        "channelId": "UCiJr4MX-DrlKgLYC0luCjpQ",
        "twitterId": "@phio_alchemist"
    },
    {
        "channelId": "UCKxRcBNKIIYHmAfqm_xDKrg",
        "twitterId": "@WillWisteria"
    },
    {
        "channelId": "UCjCZhDLsl_-AqlR-Kkn_RBg",
        "twitterId": "@Antinseijin"
    },
    {
        "channelId": "UCnvoQdObCS2VsmciF4LnvYw",
        "twitterId": "@komachi_nono"
    },
    {
        "channelId": "UCJH_UG6vN8fMZE7OH0BrkZg",
        "twitterId": "@hernes_vr"
    },
    {
        "channelId": "UCxOErQIr3Zv6W_YxFbht4gw",
        "twitterId": "@kamikinu"
    },
    {
        "channelId": "UC3-jXrZXv-PQshpaTQpicPQ",
        "twitterId": "@SakurazukiKanon"
    },
    {
        "channelId": "UC5ILsOVPu0-0ZdGKGoabnSQ",
        "twitterId": "@Riiko_nk5"
    },
    {
        "channelId": "UCrAq8h6Q3xGxzUC-84YD9PQ",
        "twitterId": "@Aoneko_Aim "
    },
    {
        "channelId": "UCYpu7V31Si5rHUFkS9aNPpw",
        "twitterId": "@terunari"
    },
    {
        "channelId": "UCRrJOT-K38VNeS3ukQARIZw",
        "twitterId": "@rimukoro"
    },
    {
        "channelId": "UC_cCW1xmXwRFp1tX-RD2X1Q",
        "twitterId": "@nanamirona"
    },
    {
        "channelId": "UCrxrLyFKqeq3fJh-OkrAn5Q",
        "twitterId": "@TsukimiYumeno"
    },
    {
        "channelId": "UC0QzO6nK1cEDZvJSt2769Zw",
        "twitterId": "@harddeluxe"
    },
    {
        "channelId": "UCSCmu_VjL4RR7rBjrvSAwSg",
        "twitterId": "@PIROPARU"
    },
    {
        "channelId": "UCMeFjJJ-0phOKMEXY2Dr-ag",
        "twitterId": "@axes_so"
    },
    {
        "channelId": "UC5u-VD8k8i8xneMtnWet_9Q",
        "twitterId": "@Tetra_VTuber"
    },
    {
        "channelId": "UCq6EBsKaFIUpac6fPkGu2PQ",
        "twitterId": "@V_insidechan"
    },
    {
        "channelId": "UCYhvWgtwFXu0YfdGjTOdkTQ",
        "twitterId": "@_konomiyako"
    },
    {
        "channelId": "UCezfmwKc2B8dtVIAgRHXrKQ",
        "twitterId": "@KotobukiYume"
    },
    {
        "channelId": "UCIM1jeOZkV9h-jfZkXQgIEg",
        "twitterId": "@kamisama_kamich"
    },
    {
        "channelId": "UCM6ZAX8qPfCzEkKcGOFWPMw",
        "twitterId": "@Ciel_Tadase"
    },
    {
        "channelId": "UCevP1FJ45OVUQqTUVuEc60w",
        "twitterId": "@inu_sion_dog"
    },
    {
        "channelId": "UCPwSREC85pZ3_ZW1MbEWf9Q",
        "twitterId": "@Sora_Tsukiyo"
    },
    {
        "channelId": "UCXZT-ezVmaLSazjE1Tr_gKA",
        "twitterId": "@anene_Vtuber"
    },
    {
        "channelId": "UCnwSu_izX1OMhzXmOEXVgxw",
        "twitterId": "@virtual_JoyuVIC"
    },
    {
        "channelId": "UCJJWLeh3h0QAO3m7FgTCOUg",
        "twitterId": "@Sakura_Maychan"
    },
    {
        "channelId": "UCMxKcUjeTEcgHmC9Zzn3R4w",
        "twitterId": "@oiran_yugiri"
    },
    {
        "channelId": "UCqZSYoJjz8EHK8_OdxnRgPQ",
        "twitterId": "@Kalmia_Xillion"
    },
    {
        "channelId": "UC87CjwiJ7_SRvuxQMQ-q-6w",
        "twitterId": "@hinase_sakura"
    },
    {
        "channelId": "UC_KmO_1xVEBS1FVDDEwp99g",
        "twitterId": "@Naoki_Ch"
    },
    {
        "channelId": "UCb-2y_Y3TfafWCtPL0ZsfpA",
        "twitterId": "@_todajun"
    },
    {
        "channelId": "UCsiKFVHkQSMlSe0vaCG0anw",
        "twitterId": "@MeaYoutuber"
    },
    {
        "channelId": "UCuSa7XbCQ5MiEIPkZxvTUDQ",
        "twitterId": "@Kokona_Yume"
    },
    {
        "channelId": "UCXS_g5Db9SHYg6Won4I13ig",
        "twitterId": "@grapefruit_uhr"
    },
    {
        "channelId": "UCoM_XmK45j504hfUWvN06Qg",
        "twitterId": "@narusenaru_2434"
    },
    {
        "channelId": "UCRXWeNnN-xuK7cpOW482oLQ",
        "twitterId": "@egglisnn"
    },
    {
        "channelId": "UCtCXaX0zEvYSgdkp-Po24TQ",
        "twitterId": "@nijinomahoro"
    },
    {
        "channelId": "UCIkifM3QoL2BP2rwYcyetGg",
        "twitterId": "@yokato_ch"
    },
    {
        "channelId": "UCHV-tYWznbEMFWoT0_oKmLQ",
        "twitterId": "@8gatsu2yuki"
    },
    {
        "channelId": "UCE304024k6EDs9Yr1Mb7T6A",
        "twitterId": "@phi_channel"
    },
    {
        "channelId": "UC92P2SH7oQqGlJAwQCW5Riw",
        "twitterId": "@mae_44_s_714"
    },
    {
        "channelId": "UCp-8cPCziyRz2OXJWBOjsCQ",
        "twitterId": "@saekiyahiro"
    },
    {
        "channelId": "UCE5rWcDxLPaaUFWOxzJFfNg",
        "twitterId": "@VAngelf_Riel"
    },
    {
        "channelId": "UCjHnkFgjwvnFw17QxYmI7fw",
        "twitterId": "@tamanoumika"
    },
    {
        "channelId": "UCksCLL04bRIe61wnzZ7vXRg",
        "twitterId": "@takamineiori"
    },
    {
        "channelId": "UChN7P9OhRltW3w9IesC92PA",
        "twitterId": "@morinaga_miu"
    },
    {
        "channelId": "UCkBCT3Woh9LXWPV28-aZ_3g",
        "twitterId": "@virtualalpaco"
    },
    {
        "channelId": "UC_HrzgYmapddmGSfn2UMHTA",
        "twitterId": "@dokuganP"
    },
    {
        "channelId": "UC4z_44S_KifPNmKrSzaEgCQ",
        "twitterId": "@citail_pr"
    },
    {
        "channelId": "UC7yqc24BjJwi3PoqhXrx6og",
        "twitterId": "@tammy_now"
    },
    {
        "channelId": "UCtj391Z3PBxq2MKq0b1-dxw",
        "twitterId": "@lull_luzyca"
    },
    {
        "channelId": "UCJzg5k2prEhTPMoK0kcBQPg",
        "twitterId": "@OtonashiRhythm"
    },
    {
        "channelId": "UCOXumOju1oSdyHysRfnQAmA",
        "twitterId": "@satouholmes"
    },
    {
        "channelId": "UCWHIyOtByBzVpmYbdncCycw",
        "twitterId": "@YUUHAM_official"
    },
    {
        "channelId": "UCCvInijwD6Qg9xwdtYJcYtQ",
        "twitterId": "@Mai_Futari"
    },
    {
        "channelId": "UCK6iAvM8b__ft-ABdDCvQng",
        "twitterId": "@emma_hazy"
    },
    {
        "channelId": "UCO4BxlTtmDlkZ5rqxDGcrGw",
        "twitterId": "@koma_shibari"
    },
    {
        "channelId": "UCnqDxEcVsvt7WpDy0px1HgA",
        "twitterId": "@oda_nobu_ga"
    },
    {
        "channelId": "UCF5_KY0GBDxQyLASpnZ8Y2w",
        "twitterId": "@Mayoi_Sakyu"
    },
    {
        "channelId": "UC61P6oww6JXAJ6NYT_b5_Vg",
        "twitterId": "@_takigawamiu"
    },
    {
        "channelId": "UCjOqQvf4u1mlzRNaphEbc7A",
        "twitterId": "@_maruyamaakane"
    },
    {
        "channelId": "UCrSpZbNNao8YQ5aj2Jr2exw",
        "twitterId": "@ayamina_Aya"
    },
    {
        "channelId": "UCk4BQkzb4Xe96kEx5RtBb-w",
        "twitterId": "@takasaki_Vtuber"
    },
    {
        "channelId": "UCH9DjwkMq9P6yGioc0-NaJg",
        "twitterId": "@amanemaho"
    },
    {
        "channelId": "UCGiZyCnfS4dmwukDnIo1K9w",
        "twitterId": "@Naea_VTuber"
    },
    {
        "channelId": "UC8jskpQfW9fn2NLK3PdaGdg",
        "twitterId": "@Kanau_Yumekawa"
    },
    {
        "channelId": "UCwx6UL368Zb8ruqo8aeZexA",
        "twitterId": "@Motoyama_Rano"
    },
    {
        "channelId": "UCOsoM1Y26DlmVCON4Ng9NNQ",
        "twitterId": "@wasabi_rinne"
    },
    {
        "channelId": "UCTzEgqLg0xc7xKBZlT7J7wQ",
        "twitterId": "@thumbsbobosan"
    },
    {
        "channelId": "UCk5zqyMfnF4HV1KQA8WCh0Q",
        "twitterId": "@cosmo_ruru"
    },
    {
        "channelId": "UCLMC54YctropOupFX8jyz9A",
        "twitterId": "@Else_PJblue"
    },
    {
        "channelId": "UC3iADAOxtcRfHr_hQZrVtUA",
        "twitterId": "@Lionel_Chienia"
    },
    {
        "channelId": "UCiJs55TAqhMfj-H-BA5RwxA",
        "twitterId": "@astrophys_tan"
    },
    {
        "channelId": "UC07A6wyM1JOnse55kGChvPg",
        "twitterId": "@_saitonicole"
    },
    {
        "channelId": "UCpPuEfqwYbpn7e2jWdQeWew",
        "twitterId": "@Mia_Mizugame"
    },
    {
        "channelId": "UCRFDXPGghaPexzgBb_Xm2CQ",
        "twitterId": "@kgRay_mj"
    },
    {
        "channelId": "UCIaC5td9nGG6JeKllWLwFLA",
        "twitterId": "@Alicemana_v"
    },
    {
        "channelId": "UCTcGbTH9hlScXB-Bm1D4HNQ",
        "twitterId": "@dead_seasons"
    },
    {
        "channelId": "UCBOZnTGPTpDI6RFXNcLhWuQ",
        "twitterId": "@_tachikawaayaka"
    },
    {
        "channelId": "UCtaVmxvdmhTs3sc39DFqsBA",
        "twitterId": "@VR_W_Raccoon"
    },
    {
        "channelId": "UC9rwQW3jUK6Xb3aOgqnhyzg",
        "twitterId": "@erikarina_vtube"
    },
    {
        "channelId": "UCVqIgBYypTt9OuOC-3dyjMA",
        "twitterId": "@mayoi_4224"
    },
    {
        "channelId": "UCl3jPsnhZNprn1sqdl8P-mg",
        "twitterId": "@wrench_t"
    },
    {
        "channelId": "UCUJMLacpivvxsWMuxMRkudA",
        "twitterId": "@Sophia_Code"
    },
    {
        "channelId": "UCuqcPmdBvwHEWGx00XYCFWg",
        "twitterId": "@futabashione"
    },
    {
        "channelId": "UC5CwaMl1eIgY8h02uZw7u8A",
        "twitterId": "@suisei_hosimati"
    },
    {
        "channelId": "UCi9gdfm7a2nAcirmD_h876g",
        "twitterId": "@odakudao"
    },
    {
        "channelId": "UCuJpyIPTENcIMpdqGYCU6WA",
        "twitterId": "@hakuno_imasaka"
    },
    {
        "channelId": "UCwcV0qAyx37ZoxeJIS_Gv5g",
        "twitterId": "@Abaraya_0112"
    },
    {
        "channelId": "UCbckfs6B6n0kpL9gFN3LmGA",
        "twitterId": "@kiran_yu"
    },
    {
        "channelId": "UCHooCsg7FEVBGVKUE_RR0DA",
        "twitterId": "@Kurumi_Ojisan"
    },
    {
        "channelId": "UCvjOsWQQpKAiahjQn8_GbiA",
        "twitterId": "@rorokovtuber"
    },
    {
        "channelId": "UC_lhJdh0Di3mbpKACgTXu3g",
        "twitterId": "@0polygon1"
    },
    {
        "channelId": "UCDYQVIyIu1RS2iclKYEXzlg",
        "twitterId": "@hakuya_virtual"
    },
    {
        "channelId": "UCF1JdALrXgub24weQpqDy9Q",
        "twitterId": "@nArUtO_kOgAnE"
    },
    {
        "channelId": "UCdOiaZl2VRPTDh6UORJcypg",
        "twitterId": "@AyaaaRiL"
    },
    {
        "channelId": "UCKR1ypkrizLHtDjyHdil3Dw",
        "twitterId": "@tura_4000"
    },
    {
        "channelId": "UC5mEZb86YXE3blczu-dIRtw",
        "twitterId": "@yousei_hayanie"
    },
    {
        "channelId": "UCVQnmM4bJYqWzcExK74sm-g",
        "twitterId": "@kuroi_riku"
    },
    {
        "channelId": "UCGqL0gaVfP-j5IZX7-cE2lg",
        "twitterId": "@Shiratori_Amaha"
    },
    {
        "channelId": "UC6gpXa7q5HMznbXZxdnS8og",
        "twitterId": "@yui_hibiki_ch"
    },
    {
        "channelId": "UCs4GryX70IEK3MkLdhDqibg",
        "twitterId": "@Rui_Squirrel"
    },
    {
        "channelId": "UCiMG6VdScBabPhJ1ZtaVmbw",
        "twitterId": "@nazuna_kaga"
    },
    {
        "channelId": "UCCJlAOB0PI3rZQIbC9U9q8A",
        "twitterId": "@tousanhamusyoku"
    },
    {
        "channelId": "UCw_VMnV67muXs-uZr-xyADA",
        "twitterId": "@FinOji_ch"
    },
    {
        "channelId": "UCNV41fU_c4IvhrwHhGKSWLA",
        "twitterId": "@paka_el"
    },
    {
        "channelId": "UC8tV-SR70N2oebYcB3iIMnQ",
        "twitterId": "@nanashi_adelie"
    },
    {
        "channelId": "UC6SYW9BpOHDqpI2X6a7DzRA",
        "twitterId": "@Toka_Mili"
    },
    {
        "channelId": "UCrhx4PaF3uIo9mDcTxHnmIg",
        "twitterId": "@par1y"
    },
    {
        "channelId": "UCmTcayoDVo7HXAAV_mquHEg",
        "twitterId": "@_uniunico_"
    },
    {
        "channelId": "UCBVmC7fKfYONkWpb2FseRSg",
        "twitterId": "@WAKANA_RAY"
    },
    {
        "channelId": "UC7HljgIDR-1P9mfwbvpbTZA",
        "twitterId": "@hatano_vtuber"
    },
    {
        "channelId": "UCa8OnR-Qm9-h9yOZaMyShpg",
        "twitterId": "@cyberpunk_ROL"
    },
    {
        "channelId": "UCMXKL1LgqMILqdavdc0DtVQ",
        "twitterId": "@kiminoyumeka"
    },
    {
        "channelId": "UCvBj7v6uknNe7JdS7bE9QvQ",
        "twitterId": "@RanmaruChannel"
    },
    {
        "channelId": "UCLhRqrcPauOgC6MTRhlOSMQ",
        "twitterId": "@VtuberDCD"
    },
    {
        "channelId": "UCEOSZye3-lJI6-VdI34Bbrg",
        "twitterId": "@heart_heartful"
    },
    {
        "channelId": "UC37QJeT8wHMoZlMasJ7CEbw",
        "twitterId": "@aomichi_akato"
    },
    {
        "channelId": "UCqKCfCEKed9wdmJhs1w1DAw",
        "twitterId": "@HoshinaHinaka"
    },
    {
        "channelId": "UCDgH-CfHO85D0rxtXnXeN2w",
        "twitterId": "@KanameMahiro"
    },
    {
        "channelId": "UCsAzaxwiKWolOWLH1bIU3wA",
        "twitterId": "@irodorimayoi"
    },
    {
        "channelId": "UCYy-CNsOseAmBYWM7oskLYg",
        "twitterId": "@uwabamisnake"
    },
    {
        "channelId": "UCjY6q7W4tmLeC2zKpoFjD8Q",
        "twitterId": "@Mogura_AI"
    },
    {
        "channelId": "UChU-HiSDcPA2P1f6U2RsXDA",
        "twitterId": "@oboroproject"
    },
    {
        "channelId": "UC5zP25Iu_cN6_B58I3OAkYQ",
        "twitterId": "@nightMEA_info"
    },
    {
        "channelId": "UCBiJHt0WEb3GGayMyUz5QIQ",
        "twitterId": "@HakariTenbin"
    },
    {
        "channelId": "UC6UwdMiDJfyjEipxJ66ceUg",
        "twitterId": "@antares_eleki"
    },
    {
        "channelId": "UCyLGcqYs7RsBb3L0SJfzGYA",
        "twitterId": "@sumire_kaga"
    },
    {
        "channelId": "UCS2qXRmxdIeBeITv4lY4qQQ",
        "twitterId": "@chris15fam"
    },
    {
        "channelId": "UCKrpKQm7Ksn4_rug7wYnetw",
        "twitterId": "@No_No_Gi"
    },
    {
        "channelId": "UC0e6zo8oX6ISSBjPaSZsjeA",
        "twitterId": "@choueki_tarou"
    },
    {
        "channelId": "UCZk6mxfTpjuuxgqxuFBJO_g",
        "twitterId": "@Engine_Kazumi"
    },
    {
        "channelId": "UC0-5wjMW1Gx3ej5V4uNoXRQ",
        "twitterId": "@hoshina_com"
    },
    {
        "channelId": "UC2bF2YxqbMlPcQ87fcd80Qw",
        "twitterId": "@Nagatoro_Koyori"
    },
    {
        "channelId": "UCW1wmI0fBsQxENwNwH-2adg",
        "twitterId": "@yume_2930"
    },
    {
        "channelId": "UCVVkSdBNaJEM4RTB9W2nnlg",
        "twitterId": "@godhandtool"
    },
    {
        "channelId": "UCmBrGHMM-fGSO1vDknaWlGA",
        "twitterId": "@Mei_Yagiri"
    },
    {
        "channelId": "UCrWLOrJLZ6Jb1CASa6RU7sQ",
        "twitterId": "@IRIS_Fl0wer"
    },
    {
        "channelId": "UC--oTE32O37NvGS_4rS2cRg",
        "twitterId": "@odoroku_o_o"
    },
    {
        "channelId": "UCV-9cZck4I31M8jaEqRAUUA",
        "twitterId": "@Flavie_VN"
    },
    {
        "channelId": "UCFIui9sGPKMLcu9Fcij9FSQ",
        "twitterId": "@NiaTsumugi"
    },
    {
        "channelId": "UCYZl69Cby8wHyazEp8I9tlA",
        "twitterId": "@micoVtuber"
    },
    {
        "channelId": "UCGEC7udx8aOQpc_eiKob40Q",
        "twitterId": "@HaseMikoto"
    },
    {
        "channelId": "UCerH0KOGyPaC5WueExiicZQ",
        "twitterId": "@anzu_chaaaan"
    },
    {
        "channelId": "UCLtY2A5H1rs3aR8bYykhX8Q",
        "twitterId": "@PIXELKO_"
    },
    {
        "channelId": "UCxavYpm91UOgngdMCGQt0Xg",
        "twitterId": "@v_minaserui"
    },
    {
        "channelId": "UCLR49xq2jDEboKx9mTxsUAQ",
        "twitterId": "@Pati_kasikoman9"
    },
    {
        "channelId": "UCom8rCUQZP98SIXJzMwjrxw",
        "twitterId": "@imarumakita"
    },
    {
        "channelId": "UC-rEbtxBcgRCD53DzoLVGPA",
        "twitterId": "@mizunana_T"
    },
    {
        "channelId": "UC4WuSmhN_hCAbAF0gvQPCTQ",
        "twitterId": "@Azatu_Vtuber"
    },
    {
        "channelId": "UC1_lYuLo6zJhbBgAhfEPA0g",
        "twitterId": "@Hidamarilariat"
    },
    {
        "channelId": "UCPkFSuWyQv5lvqhJbg9UaOA",
        "twitterId": "@srash406"
    },
    {
        "channelId": "UCyZZMKRn-mUEkPzaqa9b6bg",
        "twitterId": "@kwa_kon"
    },
    {
        "channelId": "UCM6iy_rSgSMbFjx10Z6VVGA",
        "twitterId": "@HizukiMiu"
    },
    {
        "channelId": "UCHR0kaG6d7eU1wm17fx9Mvw",
        "twitterId": "@kotone_vtuber"
    },
    {
        "channelId": "UCGu_Yfe0HiMV4ffHvkVd9Jg",
        "twitterId": "@VtuberElmina"
    },
    {
        "channelId": "UCDU4_ITJhF4wx27bt5AarEg",
        "twitterId": "@29__Ch"
    },
    {
        "channelId": "UCnMUkJtwFh3yiFA2fB_JWJw",
        "twitterId": "@Ai_love_Man0"
    },
    {
        "channelId": "UCnp8kxpT6Z978ZEMVFn58nw",
        "twitterId": "@c_yaca"
    },
    {
        "channelId": "UCiqcxYOoL6bDzs4-RP0x5YQ",
        "twitterId": "@Hoshimiya_Gumi"
    },
    {
        "channelId": "UCvzce5i14VUY-N1FQoPqRbg",
        "twitterId": "@Cecil_Channel"
    },
    {
        "channelId": "UC0MKBVaP7nWM-FZzn81I2aA",
        "twitterId": "@sakiamaikas"
    },
    {
        "channelId": "UCpqYEiR0c1ZJdU29TKalysA",
        "twitterId": "@tamago_227"
    },
    {
        "channelId": "UC4jDjXDR4KyEK-Ld5XTPbDw",
        "twitterId": "@MIMI_chan33v"
    },
    {
        "channelId": "UCH1B9AR8sfWJVf9zcu9rbGg",
        "twitterId": "@CocoTsuki_Mane"
    },
    {
        "channelId": "UCuwSnOSd1T9O5Imh403jihQ",
        "twitterId": "@AmashitaKite"
    },
    {
        "channelId": "UCjbj7_mhBQkzdFkhb_U-SRw",
        "twitterId": "@musubi_kokoa"
    },
    {
        "channelId": "UCfRl6vl7LR8fw0eva425PbA",
        "twitterId": "@bkeygames"
    },
    {
        "channelId": "UCaQWd2sDWGPCYp66CwPoSCg",
        "twitterId": "@shibayama_azuki"
    },
    {
        "channelId": "UColTX5Aosr-q-lZMDvNLcSQ",
        "twitterId": "@MOA_gamer"
    },
    {
        "channelId": "UCY1qrEDK378Jay-0ewRfnHw",
        "twitterId": "@ponchantv"
    },
    {
        "channelId": "UCxbjRsRQ0fQoT_BuflRsqjg",
        "twitterId": "@ryousiaityan"
    },
    {
        "channelId": "UCfBpIBQkIF-zUHHHexUGY3w",
        "twitterId": "@oh_so_cute1"
    },
    {
        "channelId": "UCLQIMDHNE0ZGAiHIdMbq7dw",
        "twitterId": "@NeonNight_exe"
    },
    {
        "channelId": "UCeisWPxnHOYI-GZbeg2dGBw",
        "twitterId": "@momochi373"
    },
    {
        "channelId": "UCASf3ff9ot23mgQMQbHfw3Q",
        "twitterId": "@yukinadare"
    },
    {
        "channelId": "UCTJqQUQp9Z8HVNTF3WCaP1g",
        "twitterId": "@tenma_vy"
    },
    {
        "channelId": "UCJQMHCFjVZOVRYafR6gY04Q",
        "twitterId": "@yuno_usami"
    },
    {
        "channelId": "UC2NxerohrHjEmPQ0kYngBpQ",
        "twitterId": "@HakaseYuniAI"
    },
    {
        "channelId": "UCR1vMiGggY5jSDL_eTkXJCA",
        "twitterId": "@narukami_sabaki"
    },
    {
        "channelId": "UCP0gksnZAHR2DmqTdPRiHpQ",
        "twitterId": "@yukinnkovr"
    },
    {
        "channelId": "UCi0dkw2ybTzzHyCnG2A9omQ",
        "twitterId": "@g3cgo"
    },
    {
        "channelId": "UCt0-W53G4AecsFCg-P2ujgA",
        "twitterId": "@Mia31_sing"
    },
    {
        "channelId": "UCo1i6ply_JeRMFC02HaEvYQ",
        "twitterId": "@AmanoSeitaro"
    },
    {
        "channelId": "UCeydAPr_eoU9RWCqgeVrcSA",
        "twitterId": "@ota_25"
    },
    {
        "channelId": "UCCNXAA3Ik_csiCkTG9ixUhg",
        "twitterId": "@v_sirokuma"
    },
    {
        "channelId": "UC-N6wbssq2B8baAVeUcFsTg",
        "twitterId": "@AYARI_MIZUNASHI"
    },
    {
        "channelId": "UCpVR8pys_AS24V_gsPhGlmw",
        "twitterId": "@nenenaninu"
    },
    {
        "channelId": "UCPQMAXEjEqp3D5wepIGr50w",
        "twitterId": "@leotardbuta"
    },
    {
        "channelId": "UCMCTUv9mWhE2KH4yG3KX_VA",
        "twitterId": "@namako_plum"
    },
    {
        "channelId": "UC6B5ARoyTKS5S3-mz2WzYig",
        "twitterId": "@Average_Virtual"
    },
    {
        "channelId": "UCt_Lbl6mzIgu1fKK0aELUxg",
        "twitterId": "@HarusePOPO"
    },
    {
        "channelId": "UC4cwqcZLNNYJW4cQuoM310A",
        "twitterId": "@kyogokuemilia"
    },
    {
        "channelId": "UCycmZZio75Gsa2J5BPNeyMw",
        "twitterId": "@noely2525"
    },
    {
        "channelId": "UCd5HfRcoN4VcVdpcGzbYhjA",
        "twitterId": "@weiss_kurosaki"
    },
    {
        "channelId": "UCSV-LHXvlwnBjyB0jgfd7HA",
        "twitterId": "@kohaku_55555"
    },
    {
        "channelId": "UCTqV6u2RJE4DqfLALsGuyAw",
        "twitterId": "@tetora_CuSith"
    },
    {
        "channelId": "UCn35zDRaS1m8za_ZN2fXeqA",
        "twitterId": "@gekiuma_dog"
    },
    {
        "channelId": "UCDAXIYJCca4Ac_idzdXPqug",
        "twitterId": "@Yoruko_burbank"
    },
    {
        "channelId": "UCRtI9u0ddHldLWB27ZgxtdQ",
        "twitterId": "@iminyaminokikam"
    },
    {
        "channelId": "UCx5QOWzX0t0pr8TM2nzd6UQ",
        "twitterId": "@HiiragiUrume"
    },
    {
        "channelId": "UCBnJcqkJofBN26VELPXSB5A",
        "twitterId": "@yuki_cheriko"
    },
    {
        "channelId": "UCjgmx2RpqO252PUSncInbGg",
        "twitterId": "@eri_ayamune"
    },
    {
        "channelId": "UC0PqkGyl-uSukCWu2A9zeIQ",
        "twitterId": "@KAITON_STUDIO"
    },
    {
        "channelId": "UCBRwZ2o-d3oRrgSfDhBpYJg",
        "twitterId": "@Futainari"
    },
    {
        "channelId": "UCpvbUp_mMVJ1nUsRjoG-uAg",
        "twitterId": "@OtowaShizuku"
    },
    {
        "channelId": "UCVuUKSl9NqxiY6XTCnIWXIg",
        "twitterId": "@syounenmaid_prj"
    },
    {
        "channelId": "UCQmda33xk8eku8ksxPxmhqw",
        "twitterId": "@Teichi7Teichi3"
    },
    {
        "channelId": "UC63xZ54oDBkEQ690i5_4awA",
        "twitterId": "@kise_mako"
    },
    {
        "channelId": "UCrw1-i0lDQ4o87RfU0F_Isw",
        "twitterId": "@sazzaetako800"
    },
    {
        "channelId": "UCCGMrMAkh9AKMKx6JErcAww",
        "twitterId": "@TIE_FLAME"
    },
    {
        "channelId": "UCER5z_uer8BKN4v2ZtEwJCw",
        "twitterId": "@Sekaino_AAU"
    },
    {
        "channelId": "UCLe5X1McJAzrbKVknf-WmbA",
        "twitterId": "@minimamu1027"
    },
    {
        "channelId": "UCmHm73oWhlteyc8UllbEg9g",
        "twitterId": "@VR_Uch"
    },
    {
        "channelId": "UCqWun7Xt7bfCOXMN_ofTCpA",
        "twitterId": "@Red_Ra1ncoat"
    },
    {
        "channelId": "UCOk9jmuNM4z2USwPxoSnyYg",
        "twitterId": "@akumano_goat"
    },
    {
        "channelId": "UCCg-3VRaX8TiMG9dTeKzCpQ",
        "twitterId": "@kiri_Vtuber"
    },
    {
        "channelId": "UCWG5dZHAt5DPNc6JPQ3wZow",
        "twitterId": "@kataoti_30"
    },
    {
        "channelId": "UC2FUxq6IOn_tzfOTnLkKZUw",
        "twitterId": "@yashinseigi"
    },
    {
        "channelId": "UC3uUvmAEpMb6Pqilssmyksg",
        "twitterId": "@Ten_Amagi"
    },
    {
        "channelId": "UCT-X3FxEf6CATUWjt-hzvVA",
        "twitterId": "@virtualhoneycr1"
    },
    {
        "channelId": "UCmaAwCO0zr8NEirwPsFBw6w",
        "twitterId": "@Ibuki_Rem"
    },
    {
        "channelId": "UCyxRYmzSSQF4qxohIpCrtiA",
        "twitterId": "@kobayakawa_nana"
    },
    {
        "channelId": "UCOCIOfX8iDq7t7MHc5WuWUg",
        "twitterId": "@youtaso_taso"
    },
    {
        "channelId": "UCRXBTd80F5IIWWY4HatJ5Ug",
        "twitterId": "@hanazono_serena"
    },
    {
        "channelId": "UCw8fnw2VU_Owj9bsPx1CP5g",
        "twitterId": "@vdproject_china"
    },
    {
        "channelId": "UCFB67P2h0kTTmS3Jwi9jEhw",
        "twitterId": "@akesato_vtuber"
    },
    {
        "channelId": "UCGtlmg3euSFTbg44JnZhnbA",
        "twitterId": "@sekiyoku_fina04"
    },
    {
        "channelId": "UCBJK3Acacldm7Yvec055QgQ",
        "twitterId": "@sorano_momoka"
    },
    {
        "channelId": "UCpAcI-1ZUZVBNXzAd7pTMAA",
        "twitterId": "@potapota_ramen"
    },
    {
        "channelId": "UCzAxQCoeJrmYkHr0cHfD0Nw",
        "twitterId": "@datenti_yua"
    },
    {
        "channelId": "UC6EAioKr8JTYVXk54i7-J5w",
        "twitterId": "@barzam154__"
    },
    {
        "channelId": "UC2pZbfaSvWGNQmabt-L4Cig",
        "twitterId": "@taketori_karuta"
    },
    {
        "channelId": "UCjbtwMOGYuSp_o11omDXUQQ",
        "twitterId": "@Mimic_Tetra"
    },
    {
        "channelId": "UCA5VKlK7btrutgXF4R2wnrw",
        "twitterId": "@Alicia_VRYT"
    },
    {
        "channelId": "UCmF8vbhCfXxMuHaGsnEy4DQ",
        "twitterId": "@Rimimu_omocha"
    },
    {
        "channelId": "UCDJLsqF3hnn4n3yN-OBX87Q",
        "twitterId": "@Mayaka_Tech"
    },
    {
        "channelId": "UCcjGRuOIhGjHktNC-iI37IA",
        "twitterId": "@analognihonnhei"
    },
    {
        "channelId": "UCZWhk7FpPmn7qCdepfrZrIA",
        "twitterId": "@Meltymagic__"
    },
    {
        "channelId": "UC5IfrlYhoZiHv4TFeni_zxA",
        "twitterId": "@Serina_Himekawa"
    },
    {
        "channelId": "UCkxGPGlk9AZA58vvIuVRGog",
        "twitterId": "@hanemiya_noa"
    },
    {
        "channelId": "UCLFbcm_S6qxlIt-jpetW6_A",
        "twitterId": "@chio_irama"
    },
    {
        "channelId": "UCY_qeb4tQVUeDPDYipMUoGw",
        "twitterId": "@MIAL_Vtuber"
    },
    {
        "channelId": "UCLptNnG_fCrRxQoss-fNJ0w",
        "twitterId": "@Shade0123"
    },
    {
        "channelId": "UCK72PAXy0T6v49CDgLzzOIQ",
        "twitterId": "@_Isoramanami"
    },
    {
        "channelId": "UCf57-IJn5mUJDyqd9uNEmrg",
        "twitterId": "@ringo_0_0_5"
    },
    {
        "channelId": "UCtzZEx6zvmZuMqvn0M2P9cA",
        "twitterId": "@HanamachiSumire"
    },
    {
        "channelId": "UCY6_e0cIUo3nI8LKhvBewxA",
        "twitterId": "@OculusTan"
    },
    {
        "channelId": "UCf6J4I7NwMXtuIU8YZKAjCA",
        "twitterId": "@kohaku_yuiga"
    },
    {
        "channelId": "UCcqCHOzqi5c0j1tBd0h5j2Q",
        "twitterId": "@krym_vtuber"
    },
    {
        "channelId": "UC_6ud-c7LtItRiAweXyqG8A",
        "twitterId": "@manKirala"
    },
    {
        "channelId": "UCnK6aCU0ZTRXyrKkaXd-RMg",
        "twitterId": "@Teto_Kototsuki"
    },
    {
        "channelId": "UCbHIbD9rz7BPrzakXOj_6Lg",
        "twitterId": "@asamiyayuri"
    },
    {
        "channelId": "UCxU9F9sZJdzectps34GuSyA",
        "twitterId": "@B2xmisa"
    },
    {
        "channelId": "UCtCeCDawas1DBNKHAxnc2FQ",
        "twitterId": "@higashi444"
    },
    {
        "channelId": "UCDD4T2dFbN9B9W-SJ-t22Vw",
        "twitterId": "@VirtualSurprise"
    },
    {
        "channelId": "UCD7XoYTbtoQzdmiXZK2Zycg",
        "twitterId": "@xusagi0508"
    },
    {
        "channelId": "UCFOccbf0Hq-tPs71EL8dAfw",
        "twitterId": "@ryugu_ura"
    },
    {
        "channelId": "UCfz1RFufH9MFsADnhAdXW7g",
        "twitterId": "@A_ReikaS2"
    },
    {
        "channelId": "UCuVnOISQ9bbUMjS3Kwz7Z1g",
        "twitterId": "@Vtuber_Setuna"
    },
    {
        "channelId": "UCL_zJRLImq8gpfpkz3xEfjQ",
        "twitterId": "@Mokatuber"
    },
    {
        "channelId": "UCqhnvjASWaS1eF_023Y--DQ",
        "twitterId": "@she_is_wired"
    },
    {
        "channelId": "UCsHoMIiPTvZFsPLtdLgYNng",
        "twitterId": "@yokoi_bitko"
    },
    {
        "channelId": "UC9mqVHMqp11sShAw462MrGg",
        "twitterId": "@Mikage_mone"
    },
    {
        "channelId": "UCZZ0iFMACO4R8RD-5lKVSoQ",
        "twitterId": "@makinose_makino"
    },
    {
        "channelId": "UCT8i8iDWmhVPqMf-6-fB8cg",
        "twitterId": "@Hoshi_Tefu"
    },
    {
        "channelId": "UCuQhm-iOnRpAiyDq64gUk3w",
        "twitterId": "@KimashiTowerP"
    },
    {
        "channelId": "UCM-fjG74PEH9LVMEo0H7F0w",
        "twitterId": "@GEPAI_"
    },
    {
        "channelId": "UCo1e2zlkPYxRoRQRbTkxQgQ",
        "twitterId": "@solt_pepper_"
    },
    {
        "channelId": "UCMAc88lqzqGV0uxgw9JDj0w",
        "twitterId": "@kotonoha_yukino"
    },
    {
        "channelId": "UCWhyjy7jn6VW0E73hVPtKTg",
        "twitterId": "@ShironoYuzuki"
    },
    {
        "channelId": "UC32HlZsC2tfbkDisSLnmM_A",
        "twitterId": "@emoco_art"
    },
    {
        "channelId": "UCoxRb4xKGwDUFKH8Ludjvfg",
        "twitterId": "@Maya_Ichimonji"
    },
    {
        "channelId": "UCF9j_BIh3ULTZHsyGdrTn-w",
        "twitterId": "@hachiten8"
    },
    {
        "channelId": "UC8I6muAfbssUui6Ocb1MIyw",
        "twitterId": "@maohwanwan"
    },
    {
        "channelId": "UCelr81whektFuPgFgpoTxZg",
        "twitterId": "@usano_usako_vr"
    },
    {
        "channelId": "UCnn-E8kKPKjEJCowTVxgbeQ",
        "twitterId": "@Nenene_agh"
    },
    {
        "channelId": "UCWd6oovTZBdzELQg9iRED-w",
        "twitterId": "@natu_k_"
    },
    {
        "channelId": "UCbntm8BJbien-JF1P1_usfg",
        "twitterId": "@HimetsuruS"
    },
    {
        "channelId": "UCHVHqjhfT9apG68r3MJ5McA",
        "twitterId": "@nadehana_ggy"
    },
    {
        "channelId": "UCEglcysmI63aLNTGXrR9pnA",
        "twitterId": "@Icy_V_Solid"
    },
    {
        "channelId": "UCUS2n-dVmo3E_4t5TwllsMA",
        "twitterId": "@KemominTouhou"
    },
    {
        "channelId": "UCnLhe2IzZH7ASVA4cMfgTgQ",
        "twitterId": "@kosiba_nigiri"
    },
    {
        "channelId": "UCbmZa8unWj-rMRDDE2HNprg",
        "twitterId": "@Omiki_Uwabami"
    },
    {
        "channelId": "UCh3bQf20rJnEtiU25vIK2Hg",
        "twitterId": "@denpachannel"
    },
    {
        "channelId": "UC2um9MgjkZ1CD6lKsuNQ5XA",
        "twitterId": "@gillie_yomakura"
    },
    {
        "channelId": "UCSSvuPqF_9oAXzMU_dg45_A",
        "twitterId": "@seri_nu511"
    },
    {
        "channelId": "UCT0GhQ7cs_TOIwWoDUhKRbw",
        "twitterId": "@shio_pgm"
    },
    {
        "channelId": "UC2_gcrdkZfUDQeyEyC6AjZA",
        "twitterId": "@muni_hime"
    },
    {
        "channelId": "UCAOxWcMs-bkrntzORUwEfqw",
        "twitterId": "@PoliticsMinchan"
    },
    {
        "channelId": "UClenqj9y-Lxed2DDI1ol77A",
        "twitterId": "@ochatboys"
    },
    {
        "channelId": "UCJEpGdadojQ-510MGZe3Y8A",
        "twitterId": "@nemu_kawa"
    },
    {
        "channelId": "UCL3s9kOzkK9wdYL_iqr5tuw",
        "twitterId": "@Scarlet_Sky_"
    },
    {
        "channelId": "UCS1knzJl5den7o-jeEOZuBQ",
        "twitterId": "@AkabaYukino"
    },
    {
        "channelId": "UCvUWlu7YCjCZMnmXSTd4q-A",
        "twitterId": "@inori_ch_melike"
    },
    {
        "channelId": "UCKFkfyLMNhDzaNJPhOYNCbA",
        "twitterId": "@akitsumitsuba"
    },
    {
        "channelId": "UCc32jRyXfJBSZg9_EDXceTA",
        "twitterId": "@SouTou_VTuber"
    },
    {
        "channelId": "UC5QMptQegIRiIFPma5z3wew",
        "twitterId": "@shiroyuno_ch"
    },
    {
        "channelId": "UCVHykctvqUX1fhARnxv10ZA",
        "twitterId": "@nurunuru_nurume"
    },
    {
        "channelId": "UCaWuiIyX89dLP5H4pA7QAvQ",
        "twitterId": "@XFlareVtuber1"
    },
    {
        "channelId": "UCcnIE2Nxjd-My0aaoeAWUVA",
        "twitterId": "@YunomiYuno_"
    },
    {
        "channelId": "UCbF5xOeqwFJuiV5YIBohqtw",
        "twitterId": "@Vtuber_Mochio"
    },
    {
        "channelId": "UCLwKMSOJKtoqbrCLAuiavZQ",
        "twitterId": "@kunoichiko"
    },
    {
        "channelId": "UCqt-TzsVU53WYYmj9m0ExUA",
        "twitterId": "@kohack_v"
    },
    {
        "channelId": "UCVMD_K2OoIeoPAeavlha0_A",
        "twitterId": "@amanohikari_ch"
    },
    {
        "channelId": "UCAp85e99YAwRlz9u8UljpPQ",
        "twitterId": "@vitaone_"
    },
    {
        "channelId": "UCe9nP90-eiuXLmhhEkNbUDQ",
        "twitterId": "@Pandora_ryusei"
    },
    {
        "channelId": "UCxMai3WANwU2ye8vBZ833MA",
        "twitterId": "@NewsVtuber"
    },
    {
        "channelId": "UC1iUuVnsTN9KzdAc85Y9JHQ",
        "twitterId": "@Murata_Jinro"
    },
    {
        "channelId": "UCY_2D7S_rTS9cxIGbSWF5nw",
        "twitterId": "@poemu_saotome"
    },
    {
        "channelId": "UCC_6-o2BmUBQY-qXGPXEFnw",
        "twitterId": "@Arisagame1"
    },
    {
        "channelId": "UCZkTIpbHp0W8-mT0fEhQE8w",
        "twitterId": "@belsama241"
    },
    {
        "channelId": "UCBQd84IW8OvM8H5jftHdvmw",
        "twitterId": "@kamishiro_kurea"
    },
    {
        "channelId": "UCBLByeZyx5DGjvEUcZT6Alg",
        "twitterId": "@yamada_suzumeP"
    },
    {
        "channelId": "UCNs3YHAyoXMw4WFJyhB-GuA",
        "twitterId": "@anemone_rose_"
    },
    {
        "channelId": "UC3oBThiJHOSA4B2S4qdFMyw",
        "twitterId": "@syuthii"
    },
    {
        "channelId": "UCF-VYfBjb7uupcdELrrB58A",
        "twitterId": "@VirtualBa7"
    },
    {
        "channelId": "UCFDOwDyhBOZz8z2ibuGqFfg",
        "twitterId": "@IMAWAMADA_seiga"
    },
    {
        "channelId": "UCWgnqQ6hPoWmgyIZxA9dr1A",
        "twitterId": "@bukimi_ch6"
    },
    {
        "channelId": "UCJG86VvFErqEwiHdSxjO53g",
        "twitterId": "@HabaraYutori"
    },
    {
        "channelId": "UC9LdtufHlTyBQI3IQgc7S1w",
        "twitterId": "@buriburinose"
    },
    {
        "channelId": "UC-dEENXELAMvTpizF2HE6mw",
        "twitterId": "@nekoya_syuri"
    },
    {
        "channelId": "UCOVhPT6O0-0_AopJzyeKFDA",
        "twitterId": "@nemu_tamizzz"
    },
    {
        "channelId": "UC2qxMP86cqdqftwJdEe1ABg",
        "twitterId": "@GurikoEgaki"
    },
    {
        "channelId": "UCnph4_BX3ron_hSTDCDDQ5g",
        "twitterId": "@KamentuberGo"
    },
    {
        "channelId": "UC3LJj-dWaa0wkEOYgopHq2Q",
        "twitterId": "@tensitya"
    },
    {
        "channelId": "UCy31Dtc9DrMaLRkZXUg7byg",
        "twitterId": "@Marie_Ayase"
    },
    {
        "channelId": "UCBAopGXGGatkiB1-qFRG9WA",
        "twitterId": "@usausachannel"
    },
    {
        "channelId": "UCIu-aUArYq_H84dBpCAokMA",
        "twitterId": "@Shirayuki_Reid"
    },
    {
        "channelId": "UCyywCfsoxpahmmXY3FJI5UQ",
        "twitterId": "@nishimura_114"
    },
    {
        "channelId": "UC64mkbh9upALaZfkgnrXV5Q",
        "twitterId": "@nagekino_aria"
    },
    {
        "channelId": "UCUHsCratmjA7dPbAulQi7dQ",
        "twitterId": "@Starlight_chann"
    },
    {
        "channelId": "UCvGBVyzuyIJi7Rytqo90Ekw",
        "twitterId": "@xuniJJ"
    },
    {
        "channelId": "UC7tlWCIjH6RKRt5m-Iz9Mmw",
        "twitterId": "@kikocyan_info"
    },
    {
        "channelId": "UC_P2inWOEXbx-psLhf4CZLg",
        "twitterId": "@VRUMA09"
    },
    {
        "channelId": "UCwlEjEKpBCH1AQKjZ7aAuZQ",
        "twitterId": "@Bloodemperor3"
    },
    {
        "channelId": "UCcegcJA0ijqaZUUyvGtr5xQ",
        "twitterId": "@kaniegg"
    },
    {
        "channelId": "UC1ngKt9O50C2Zz5OfqZtbwg",
        "twitterId": "@kurumi_pgm"
    },
    {
        "channelId": "UCq4g1_QdWbo9409qNATnAAw",
        "twitterId": "@origamiyusa"
    },
    {
        "channelId": "UC5dZzb_MZ0t-qoFxuUr6cLw",
        "twitterId": "@ice_noyuri"
    },
    {
        "channelId": "UCHq-FjMlPYmHqAjnW44p7hw",
        "twitterId": "@maki_michiru"
    },
    {
        "channelId": "UCTqyZRNC2W4yN0lF3esFIFw",
        "twitterId": "@Hagane_VTuber"
    },
    {
        "channelId": "UCqlbdk8XtMSxogRDNMzRrxA",
        "twitterId": "@kaluru"
    },
    {
        "channelId": "UCZtf7IVlAl0BXn5D7T3_J5w",
        "twitterId": "@mrbsmrk"
    },
    {
        "channelId": "UCjAAwpJgvnpZT5QDPwP-Y3Q",
        "twitterId": "@roseato_v"
    },
    {
        "channelId": "UCdNsLZ--HeZPiRaMag1Rpaw",
        "twitterId": "@SurvivalRabbit"
    },
    {
        "channelId": "UCfyuU4kxzyk_0f8X18MLTWw",
        "twitterId": "@Uso_Aokawa"
    },
    {
        "channelId": "UCuzyRan-_M7yBATGH7T-2uA",
        "twitterId": "@kyabetu_aomori"
    },
    {
        "channelId": "UCp01G7ZvzZh_Rn0J9QsCFbg",
        "twitterId": "@momoi__saki"
    },
    {
        "channelId": "UCprQaynf6W8Qargmo5jg2-Q",
        "twitterId": "@mekuru_chan"
    },
    {
        "channelId": "UCk91Sc3x302pquRDccWo6rQ",
        "twitterId": "@Morrinya"
    },
    {
        "channelId": "UCYDHWR7KNS_oyWMDhD7oeUg",
        "twitterId": "@siarurin"
    },
    {
        "channelId": "UCkKjuJc-WBn88fRXbzjCyEw",
        "twitterId": "@Kocha_Yuzuka"
    },
    {
        "channelId": "UCIVrA6rePXPdkdVJZKdhsRg",
        "twitterId": "@seeha_lim"
    },
    {
        "channelId": "UCDRg709kaDCG7fp3hV11kxA",
        "twitterId": "@manachan_momo"
    },
    {
        "channelId": "UC6g2dwBo5lDSuf0L-EMCo9A",
        "twitterId": "@mint15fam"
    },
    {
        "channelId": "UC7EJ9bOU9uPfbsfywy26siw",
        "twitterId": "@Lupinus_xxx"
    },
    {
        "channelId": "UCoJHEdmWNEDt5MWOZHQFTEg",
        "twitterId": "@Karura_Ouka"
    },
    {
        "channelId": "UCxAFoUJh1JrJeegm-h-RE3g",
        "twitterId": "@uru_ogami"
    },
    {
        "channelId": "UCGYSdXbiAxm7AVqPeb9CooA",
        "twitterId": "@riachan_nel"
    },
    {
        "channelId": "UCUpysYEAnksyyr1ykN8JBCw",
        "twitterId": "@Hiyori_tokiwa"
    },
    {
        "channelId": "UCri7Aft0jr2Jd0wIdTft84A",
        "twitterId": "@LeeShionVG"
    },
    {
        "channelId": "UCImadINLG_ZR2mqI_WpRfrw",
        "twitterId": "@Risa_Amanogawa"
    },
    {
        "channelId": "UCGiqBOXXtVwLLnmC124N5Ew",
        "twitterId": "@ushiwaka_shino"
    },
    {
        "channelId": "UCpHIwGHq_3OfX42cyfyJp-A",
        "twitterId": "@MiMi_KANADE"
    },
    {
        "channelId": "UCJiR17fagJ7uKSozhgFNS5A",
        "twitterId": "@15PAFE_Vtuber"
    },
    {
        "channelId": "UCkG2vRPOJ2CnlgcRO9Ah8Bg",
        "twitterId": "@Yurino_Pokemon"
    },
    {
        "channelId": "UCsrBAAinsh0kJES1yggXKWg",
        "twitterId": "@tacute3"
    },
    {
        "channelId": "UCTzHuMNvOQjEfPdIXSdA4MA",
        "twitterId": "@kokuyo_ageha"
    },
    {
        "channelId": "UCHutpyCqxldF0dIvXtAQg0g",
        "twitterId": "@Vakudaikan"
    },
    {
        "channelId": "UCmzcjeRE968SSU_jNXN8ZuA",
        "twitterId": "@asuka_aux"
    },
    {
        "channelId": "UCdhTrLS7gusvGvcXucYfy9Q",
        "twitterId": "@fujino_kranke_"
    },
    {
        "channelId": "UC1qSl6q0ZtG_AnFbrC99kaQ",
        "twitterId": "@otsuta_l"
    },
    {
        "channelId": "UC5MPVxiJwOtj1ysqjSkM5eg",
        "twitterId": "@maya4649"
    },
    {
        "channelId": "UCcHv8CrBnQn19xhokzNwWFA",
        "twitterId": "@yumeno_meika"
    },
    {
        "channelId": "UCNzSw-wJq_dYtBxiDeOIdEA",
        "twitterId": "@SatsuMai_chan"
    },
    {
        "channelId": "UCTPmeThimFesJ2YyqErKjsg",
        "twitterId": "@yurarito_VR"
    },
    {
        "channelId": "UCqkOtS8jprs1w4W2cE6uDTw",
        "twitterId": "@AmamiKoji"
    },
    {
        "channelId": "UCyTw66xE5YkeTL2YduA69QQ",
        "twitterId": "@_MinatoMinami"
    },
    {
        "channelId": "UCKwATdrcjyzNv9c56PqJbWA",
        "twitterId": "@ELENA_YUNAGI"
    },
    {
        "channelId": "UCWxLvdpcfXZVf3jvgw6uTPw",
        "twitterId": "@shihou_mikura"
    },
    {
        "channelId": "UCN3L41COcrsDsqTKa7Pgczg",
        "twitterId": "@kochou_momiji"
    },
    {
        "channelId": "UCFF8ktCy1zHw0maKPPufViw",
        "twitterId": "@ikiataribatari"
    },
    {
        "channelId": "UCBKxF1PHQtT78ypcVYmBtBA",
        "twitterId": "@ANKOchan_01"
    },
    {
        "channelId": "UClWQewYEhh2b76RbBr77ksQ",
        "twitterId": "@amaama_azuki"
    },
    {
        "channelId": "UCzrwvapp587lhoRkmjKPDiA",
        "twitterId": "@saionji_marilyn"
    },
    {
        "channelId": "UCnqnQYvBehuaAYi9M8W_cig",
        "twitterId": "@Pvtuber"
    },
    {
        "channelId": "UCQlXGu43ms0xBUEPh7Mx8fA",
        "twitterId": "@gol559"
    },
    {
        "channelId": "UCf5j5cluZNyAA8J3XUa6C8w",
        "twitterId": "@Akane_Irosaki"
    },
    {
        "channelId": "UCw6nf_0Bx5gb2BA0nlA0MQA",
        "twitterId": "@Clearite"
    },
    {
        "channelId": "UCJWkvInYEeXbISGHSj6tNOA",
        "twitterId": "@kurone_urara"
    },
    {
        "channelId": "UC0P19Xv-120tGGpwN-b-C6Q",
        "twitterId": "@RukatuRn"
    },
    {
        "channelId": "UCpjzXt6B9UUOxi77MH85nkg",
        "twitterId": "@MiyaMiyabiVtube"
    },
    {
        "channelId": "UCflNPJUJ4VQh1hGDNK7bsFg",
        "twitterId": "@Bell_Nekonogi"
    },
    {
        "channelId": "UCRAWk5rqZVEC_qUii-jdxhg",
        "twitterId": "@italing_math"
    },
    {
        "channelId": "UCX_P_KGfAwqaBH3KdVI8smw",
        "twitterId": "@momomaru_nekuto"
    },
    {
        "channelId": "UCaojI-1O5yGxCfuH0N8bz2Q",
        "twitterId": "@lee_yayaya"
    },
    {
        "channelId": "UCEp5C-_6jXTuFydDGPbLOpw",
        "twitterId": "@Nanashi_MMD"
    },
    {
        "channelId": "UCBwdL4OKpxrq4VatfULpOAw",
        "twitterId": "@clusterVR"
    },
    {
        "channelId": "UCNy4FaMEHm1oopXkvt6qgWA",
        "twitterId": "@KagamiMeguyun"
    },
    {
        "channelId": "UCsZtpvHAE8aO5hoAstL75EQ",
        "twitterId": "@imasaku_hana"
    },
    {
        "channelId": "UC17uKGuqg7x6emXUIVvylSQ",
        "twitterId": "@mumoji2077"
    },
    {
        "channelId": "UCBCUOWzXGlgR4rYD3byQInA",
        "twitterId": "@Ryusei_Honey"
    },
    {
        "channelId": "UCjCpPu8eYSSDUmvOY4Zu_lA",
        "twitterId": "@TibaNezumi_HH"
    },
    {
        "channelId": "UCaq_BEsIHLVvdU6lCKLtipQ",
        "twitterId": "@hanakoto82"
    },
    {
        "channelId": "UCSv-sZE1vmCV3EjYccpmu9A",
        "twitterId": "@ryuji_kohinata"
    },
    {
        "channelId": "UCL131JIlSzydlXwPEI_Ob7Q",
        "twitterId": "@mifentan23"
    },
    {
        "channelId": "UCWBSYVSu1KSgfY3_ysu1LZQ",
        "twitterId": "@tukumo_V"
    },
    {
        "channelId": "UC2ZOyvRmzWLaEigd3k8GE9w",
        "twitterId": "@touko_tkys"
    },
    {
        "channelId": "UCRNkcnmM3JpngGmU-cXrzJA",
        "twitterId": "@tomako_milk_tea"
    },
    {
        "channelId": "UCMnMR24GAMCcB9kjdIulGXg",
        "twitterId": "@sakenomimiko"
    },
    {
        "channelId": "UCv2byPgvl60Mh1vQBnXuksA",
        "twitterId": "@virtualcat_poch"
    },
    {
        "channelId": "UCbwGxIDKW2W39ZNXF4XdD5A",
        "twitterId": "@Vtuber50505614"
    },
    {
        "channelId": "UC2i0wuJV-_7P9NYD6u8BAwA",
        "twitterId": "@Arr_yurisawa"
    },
    {
        "channelId": "UCd7M3i21IJiPXab50A2l6DA",
        "twitterId": "@NanaNatsume_"
    },
    {
        "channelId": "UCjPtFV_hLQNXosySm3c6CWQ",
        "twitterId": "@hitohari_nui"
    },
    {
        "channelId": "UCRUFY2ZCyVOvC-1rJIVZlKg",
        "twitterId": "@Kumonoue_Yumemi"
    },
    {
        "channelId": "UCI73A5O-_jLQWoGLokzCIOQ",
        "twitterId": "@neneko_and_Dr"
    },
    {
        "channelId": "UCx45gypxj0fME6zxsLKsNow",
        "twitterId": "@memento_vivi"
    },
    {
        "channelId": "UCiH9I4XfHuMjLsw8_0BGWww",
        "twitterId": "@VCafe_Ange"
    },
    {
        "channelId": "UCx9sSKp4rNsHonHYMNjTv_g",
        "twitterId": "@otonashi6on"
    },
    {
        "channelId": "UC7fLSw4NeZwViAz7oX54Mlg",
        "twitterId": "@inukami2266"
    },
    {
        "channelId": "UCa_c-GDWvfwrb9IadpydJLQ",
        "twitterId": "@VRSetsuna"
    },
    {
        "channelId": "UClf0kZBKcBVKVOAjGEGbQ-A",
        "twitterId": "@msr0n"
    },
    {
        "channelId": "UC2BjlkHDiWwkQ1rxFjlooyw",
        "twitterId": "@Dailechi23"
    },
    {
        "channelId": "UCSbH4JTr-ievuCVGtSvDA8w",
        "twitterId": "@AKMakame"
    },
    {
        "channelId": "UCX5Z2Y7z852NIhMOgsZhYSw",
        "twitterId": "@ekakimakuru"
    },
    {
        "channelId": "UCJU2aznHDtlixqfX-qqlzcw",
        "twitterId": "@momochimomo0414"
    },
    {
        "channelId": "UC4OZTFcH6NAtiYSbHyLwWFw",
        "twitterId": "@_Rinyou"
    },
    {
        "channelId": "UCDO3LfT7oJRKfAqwnuVvaqg",
        "twitterId": "@ASSISTANT_ROB"
    },
    {
        "channelId": "UCgpbzmJpSsmpmgdfla-KNmA",
        "twitterId": "@komainu_chino"
    },
    {
        "channelId": "UC3qm7Q7Yv0qKRZahNLgSCxQ",
        "twitterId": "@Solt_vdoll"
    },
    {
        "channelId": "UCooOM22Vyz1qu-eCwHPytkA",
        "twitterId": "@ori_pgm"
    },
    {
        "channelId": "UCObwvQOtN76A9VzHZiWlASQ",
        "twitterId": "@nemui_hina"
    },
    {
        "channelId": "UCcYK-t2eBsvXfjw6RlmJisQ",
        "twitterId": "@monmon2434"
    },
    {
        "channelId": "UC-m51QmfolYLWL4rBULK5lg",
        "twitterId": "@TkbotEisen"
    },
    {
        "channelId": "UCrhf6HYKnV6bxyaB6ooJzbw",
        "twitterId": "@MoarinVtuber"
    },
    {
        "channelId": "UCjUkEc9oazVLsqegcjXJnEA",
        "twitterId": "@hosakimenmavt"
    },
    {
        "channelId": "UC4ojxDELqgrrn6DlzHOIIMw",
        "twitterId": "@maturihinako03"
    },
    {
        "channelId": "UC8-XixGs6a_0Q494Ebt1Vyg",
        "twitterId": "@HinaSengariFarm"
    },
    {
        "channelId": "UCdcH3JilSZSo85lnDXLP4Sg",
        "twitterId": "@ukyou_nemu"
    },
    {
        "channelId": "UCxp8AZy1RtU9klpBomXoBeg",
        "twitterId": "@UwanAkanome"
    },
    {
        "channelId": "UCqLiszx_ts8t8JD0qUQxHRw",
        "twitterId": "@HanayamaMadoka"
    },
    {
        "channelId": "UC3A5XY2_yk22ZcFKJPqy8mw",
        "twitterId": "@saziki_renka"
    },
    {
        "channelId": "UCthcBWDHlWurwtdx23rKM_Q",
        "twitterId": "@yukihime_ringo"
    },
    {
        "channelId": "UCnzwQFJpRZvec3QgTSLJpKg",
        "twitterId": "@Vtuber_Warrior"
    },
    {
        "channelId": "UCP8hJ7gjtwrO-QR9tl07djg",
        "twitterId": "@Mia_Kotone"
    },
    {
        "channelId": "UCJXKhxmatZ4Ox90YKOfgg9g",
        "twitterId": "@majo5meme"
    },
    {
        "channelId": "UCT7N1yYY-pUM_qmnH00rqnA",
        "twitterId": "@rurunadayo"
    },
    {
        "channelId": "UCofinfDNUy7n4aHfO_p71sg",
        "twitterId": "@gAVu5858"
    },
    {
        "channelId": "UCdyEhrv8hWi2VE4a_DzggNQ",
        "twitterId": "@korooooo56"
    },
    {
        "channelId": "UC7u62iqNSv6_BMLCZFn6bDA",
        "twitterId": "@tomee07"
    },
    {
        "channelId": "UC1X6VvfpSrxhhNgmVs8_8qQ",
        "twitterId": "@Guestman_cy"
    },
    {
        "channelId": "UCN00mjuLh6fXZpf-PTVXEzg",
        "twitterId": "@EruKiraVSGundam"
    },
    {
        "channelId": "UCyMFtAM6ojYfZakbRcRT3og",
        "twitterId": "@MaliceWocky"
    },
    {
        "channelId": "UCu0aKD_tvYuhAQff9hCRnxg",
        "twitterId": "@Ryuno_Hanabi"
    },
    {
        "channelId": "UCFIAtyXz7XgNND_2GlE6t3A",
        "twitterId": "@highkarasound"
    },
    {
        "channelId": "UCCg79cQV8I571YIFVz0lpBQ",
        "twitterId": "@sakuyaoi"
    },
    {
        "channelId": "UC8oLBzcFC-aXPd0q-WuGWSw",
        "twitterId": "@musubimeyui"
    },
    {
        "channelId": "UC9hfQXw4GsH5LY9St0c707Q",
        "twitterId": "@Nanamichan_nel"
    },
    {
        "channelId": "UCZirK6E3vPh06wXLI_dSsTQ",
        "twitterId": "@miuraunihiko"
    },
    {
        "channelId": "UC8vXEDFLTyirdc2Fs_r58Pw",
        "twitterId": "@YumenoWatashi"
    },
    {
        "channelId": "UCzhudk1GGqy94XX_S0TlRVQ",
        "twitterId": "@mitsurugi_yui"
    },
    {
        "channelId": "UCUAtAMbbUuaXkX_NVwth1WQ",
        "twitterId": "@Talency2434"
    },
    {
        "channelId": "UCaBJpskufXmLFHEr7I6_UPw",
        "twitterId": "@O2PAIGC"
    },
    {
        "channelId": "UCFU24isSE3_uaN8kT03aH7Q",
        "twitterId": "@Kitsune_Project"
    },
    {
        "channelId": "UCIo2K71MMfFdfHoO4CQnfhA",
        "twitterId": "@vy_ran_"
    },
    {
        "channelId": "UCrRFGIbsmLCD8zE7FS53eZQ",
        "twitterId": "@aoto_rabi"
    },
    {
        "channelId": "UC1MaFZ4001YJt9cVWbnFo1Q",
        "twitterId": "@MyGarurura"
    },
    {
        "channelId": "UCx9-e_Cpk-ljW79fOClSYgw",
        "twitterId": "@ZERO_VtubeR"
    }
]